[
	{
		"source_id": "25001",
		"source": "하나카드",
		"consulting_date": "2025-08-31",
		"consulting_category": "입금내역 안내",
		"client_gender": "여자",
		"client_age": "50대",
		"consulting_turns": "54",
		"consulting_length": 339,
		"consulting_content": "상담사: 상담원 ▲▲▲입니다.\n손님: 네, 여보세요?\n상담사: 예, 안녕하세요?\n손님: 네, 제가 상세 내역을 받았는데요.\n손님: 지난 번에 제가 말일 날 ▲▲▲원을 먼저 끝났거든요.\n상담사: 네.\n손님: 그런데 그 내용이 없어요. 그거는 다 끝났다고 안 보내주셨나 그 내용이 없거든요. 그거랑 같이 좀 다 보내주셨으면 하는데\n상담사: 전화 주신 ▲▲▲님 본인 맞으십니까?\n손님: 네, 네.\n상담사: 네, 손님 잠시만요.\n상담사: 손님, 그런데 이게 손님 말씀처럼 ▲▲▲원 결제하셨잖아요.\n손님: 네.\n상담사: 어 손님 잠시만요.\n손님: 그 내용까지 다 이번 달 걸로 \n상담사: 손님, 기다려 주셔서 감사합니다. 지금 손님 말씀처럼 저희 쪽에 이제, 손님 이거는 저희가 만드는 게 아니고요.\n손님: 네.\n상담사: 네, 그런데 지금 보면은 저희 쪽은 아니시고요. 그 이거 청구서 번호 혹 그 완납이라고 표기가 되어 있으신데 혹시 안 보이세요?\n손님: 아니, 완납돼 있는 게 없어요. 그냥 일시불 이거밖에 안 왔거든요.\n상담사: 그 일시불 금액 혜택 구분에 완납이라고 되어 있으세요.\n손님: 아니요, 없는데 그렇게는 없고요.\n손님: 이게 지금 이번 달에 했던 건데 아깝게 빠지고 이번 것만 나와 있거든요.\n상담사: 어 근데 손님, 이거는 저희가 그러면 입금하셨던 내역서는 제가 따로 이메일이나 팩스로 보내드릴 수가 있고요. 만약에 손님께서 보신 청구서에 표기가 안 되어 있다라고 하시면 이거는 이미 지금 손님 결제일이 ▲▲일이잖아요.\n손님: 네.\n상담사: 그래서 지금 보니까 금액 확정이 ▲▲월 ▲▲일 날 청구서가 만들어지는데\n손님: 네, 네.\n상담사: 손님이 청구서 만들어지기 전에 먼저 선결제하시면 그 내용이 빠졌어요, 손님.\n손님: 네, 그러니까요, 그게 빠졌는데 그걸\n상담사: 그러니까 이거는 표기를\n손님: 그걸 알고 싶다고요, 그 앞에. \n상담사: 그러니까 입금 내역은요, 이거 입금을 ▲▲▲원 입금하신 건에 대해서만 발송은 해 드릴 수 있는데 팩스 또는 이메일로 가능한데 어떤 방법이 편하세요?\n손님: 네.\n손님: 팩스로요.\n상담사: 어 팩스 있으세요?\n손님: 네, 네.\n상담사: 예, 팩스 번호 말씀 부탁드립니다.\n손님: ▲▲▲\n손님: ▲▲▲\n상담사: ▲▲▲\n손님: ▲▲▲▲▲번이요.\n상담사: ▲▲▲ 맞으세요?\n손님: 네, 끝까지 지금 네.\n상담사: 네.\n손님: 예, ▲▲월달 청구 금액이 ▲▲▲▲▲원 떴는데요.\n상담사: 네, 네.\n손님: 네, 그 ▲▲▲원 빼고 이 금액이라는 거잖아요, 지금.\n상담사: 어 잠시만요. 손님, 이거 팩스를 제가 먼저 다 보내고 하나씩 도와드릴게요. 일단은 손님 그 팩스는 제가 지금 바로 신청해 드렸고요, 이거는 이제 입금된 내역이 있잖아요. ▲▲ 입금한 내역서 관련해서만 제가 따로 발송해 드린 거고요.\n손님: 네, 네.\n상담사: 예, 그리고 저희 손님 지금 제가 보니까\n상담사: 손님 말씀처럼 지금 입금하신 내역 제외하고 나머지 금액이 지금 현재 ▲▲▲▲▲▲▲원이세요.\n손님: 네, 알겠습니다. 그럼 지금 팩스 보내셨죠?\n상담사: 네, 팩스 발송해 드렸고 30분 정도 소요되세요.\n손님: 네, 알겠습니다. 감사합니다.\n상담사: 예, 상담원 ▲▲▲이었습니다.\n손님: 예.",
		"consulting_time": "16:00"
	}
]