[
	{
		"source_id": "24204",
		"source": "하나카드",
		"consulting_date": "2025-08-28",
		"consulting_category": "이용내역 안내 ",
		"client_gender": "남자",
		"client_age": "60대",
		"consulting_turns": "37",
		"consulting_length": 282,
		"consulting_content": "상담사: 상담원 ▲▲▲입니다.\n손님: 아 예, 수고하십니다.\n상담사: 감사합니다. \n손님: 저기 지금 ▲▲카드에서 그 결제가 안 들어오는데 지금 카드 ▲▲은행인데 카드를 바꿨거든요. \n손님: 이 카드로 지금 자동이체가 되어있는 게 맞습니까? 어떻게 해야 됩니까?\n상담사: 네, 손님 확인 바로 도와드리겠습니다. 본인 확인을 위해 등록된 휴대폰 번호와 생년월일을 말씀해 주시겠습니까?\n손님: 직통 번호 ▲▲▲▲▲▲▲▲▲▲▲\n상담사: 네.\n상담사: 생년월일 말씀해 주세요. \n손님: 고유번호요?\n상담사: 네, 생년월일 말씀 부탁드리겠습니다.\n손님: ▲▲▲▲년 ▲▲월 ▲▲일\n상담사: 네, 전화 주신 손님 본인의 성함을 말씀해 주시겠습니까?\n손님: ▲▲▲\n상담사: 네, 연결된 결제 은행이 어떻게 되십니까?\n손님: ▲▲은행이요.\n상담사: 네, 소중한 정보 확인 너무 감사합니다. 현재 저희가 확인했을 때 손님께서 기존에 보유하고 계시던 ▲▲카드가 있으시고 이번에 새로 ▲▲▲▲카드를 발급해 주신 내용으로 확인되시는데요. 기존에 연결되어 있던 자동이체는 동일하게 카드 납부 처리가 되시고요.\n손님: 예 예.\n상담사: ▲▲카드 같은 경우에는 손님, 예다함 상조는요, 이 내용을 ▲▲카드로 자동이체 변경을 해 주셔야 정상적으로 할인이 가능하신 점만 참고 부탁드리겠습니다.\n상담사: 아, 자동이체를 신청한다고 해 주셨다는 말씀이세요?\n손님: 아 예, 자동이체를 해달라고 그러니까 돈을 이체로 다 그 해 놨다 그러더라고요?\n상담사: 음, 그러세요. 현재 저희가 확인했을 때 해당 내용은 ▲▲월 ▲▲일자 손님이 기존에 보유하고 계시던 ▲▲카드로 자동납부가 신청되신 거로 확인되세요. \n손님: 네.\n상담사: 해당 부분은 한 번 ▲▲ 쪽으로 문의하셔서 손님께서 이번에 발급 받으신 ▲▲카드로 자동이체 변경하시고 이용 부탁드리겠습니다.\n손님: 저건 무슨 말이죠? 그다음에 전화를 해서 뭐라 그래야 돼요?\n상담사: 네.\n상담사: 자동이체는 손님이 보유하고 계신 ▲▲카드로 변경하시겠다고 말씀해 주시면 되고요, 손님께서 ▲▲▲▲▲카드를 소지하신 상태로 전화주시면 그쪽에서 카드 번호라든가 이런 것도 물어보실 거예요. \n손님: 예.\n상담사: 한번 확인하시고 통화해보시면 이용하시기가 좀 더 편하실 겁니다.\n손님: 아 ▲▲▲▲로 해서\n손님: 기존에 쓰던 카드로 이 계좌는 자동 취소하지 않고\n손님: 새로 만든 카드로 자동이체를 한다고 이야기를 하라는 말이지요?\n상담사: 네, 맞습니다. 손님 아무래도 ▲▲카드는 예다함 상조 할인을 받으시려고 신규로 하신 거잖아요?\n손님: 예.\n상담사: 네, 그러니까 할인을 적용 받으시려면 해당 카드로 ▲▲ 자동납부 신청이 되어 있으셔야 하기 때문에 해당 내용은 한번 변경 처리를 부탁드리겠습니다.\n손님: 알겠습니다.\n상담사: 네, 상담원 ▲▲▲이었습니다.",
		"consulting_time": "13:30"
	}
]