[
	{
		"source_id": "22225",
		"source": "하나카드",
		"consulting_date": "2025-08-18",
		"consulting_category": "이용내역 안내 ",
		"client_gender": "여자",
		"client_age": "30대",
		"consulting_turns": "23",
		"consulting_length": 201,
		"consulting_content": "상담사: 상담원 ▲▲▲입니다.\n손님: 안녕하세요? 뭐 문의 좀 드릴려고 하는데요.\n상담사: 네, 안녕하세요? 무엇을 도와드릴까요?\n손님: 그 ▲▲카드를 제가 해지를 했는데.\n상담사: 네, 네.\n손님: 그\n손님: 해지하면서 그 아파트 관리비 자동 이체 해 놓은 것도 해지 돼가지고 혹시 근데 결제가 어떻게 된 건가 해 가지고요.\n상담사: 네, 네.\n상담사: 네, 제가 일단 한 번 확인해 볼 텐데 전화주신 ▲▲▲ 님 본인 맞으실까요?\n손님: 네, 맞아요.\n상담사: 어, 일단은 지금 현재 ▲▲월 ▲▲일에 카드 해지 해주신 건 확인되고 있는데요, 혹시 해지하신 카드가 지금\n상담사: 그 ▲▲카드 해지해주셨는데 지금 아파트 관리비가 이전에\n상담사: 해당 카드로 등록이 되어 있으셨던 걸로 확인되시는데요, 이게 카드가 해지가 되시면서 아파트 관리비 같이 해지는 되셨어요. 그래서 지금 ▲▲월 납부 마감 아파트 관리비는 지금 어떻게 처리됐는지 확인을 해 드려야 돼서 잠시만 기다려 주시겠습니까?\n손님: 네, 네.\n상담사: 네, 기다려주셔서 감사합니다. 이 경우에는 이제 아파트 관리비 같은 경우 납부마감일 마지막\n상담사: 날짜에 맞혀서 ▲ 영업일 전에 승인처리가 되시는데요. 만약에 ▲▲월 달 기준이시면 승인되시는 날짜 예정 날짜가 ▲▲일이셨을까요? 그런데 ▲▲일에 해지하셨기 때문에 ▲▲월 납부 마감 아파트 관리비는 카드로 승인 안 되셨어요.\n손님: 아, 알겠습니다. 그럼 아예 안 된 거예요, 결제?\n상담사: 네, 카드로 승인 안 되셨고요, 그러면 ▲▲월 납부 마감 아파트 관리비 미납처리 되셨을 수가 있기 때문에요. 그 한번 그 관리사무소 쪽으로 전화해 보셔야 돼요.\n손님: 아 네. 알겠습니다.\n상담사: 네, 감사합니다. 상담사 ▲▲▲이었습니다.\n손님: 예, 예.\n손님: 네, 감사합니다.\n상담사: 네, 감사합니다.",
		"consulting_time": "18:00"
	}
]