[
	{
		"source_id": "22495",
		"source": "하나카드",
		"consulting_date": "2025-08-19",
		"consulting_category": "결제대금 안내",
		"client_gender": "남자",
		"client_age": "40대",
		"consulting_turns": "27",
		"consulting_length": 222,
		"consulting_content": "상담사: 상담원 ▲▲▲입니다.\n손님: 여보세요?\n상담사: 예, 안녕하십니까?\n손님: 그러니까? 좀 전에 그 ▲▲카드 발급해서 뭐 체크 카드 발급비 관련해서 상담을 했는데요.\n상담사: 네.\n손님: 저하고 상담했던 상담원분 한번 다시 연결이 돼나 싶어서요.\n상담사: 아 그러세요? 먼저 ▲▲▲님 본인 맞으신가요? 어떤 부분 땜에 그러신지 알려 주시면 제가 안내 도와드려 볼게요.\n손님: 예, 예.\n손님: 그 아까 전에 그 제가 미납한 게 없는데 미납한 걸로 해 가지고\n상담사: 음 네.\n손님: 보니까 그 전에 체크 카드 만든게 돈이 안 빠져나가고 바로 그냥 해지가 돼 가지고 미납으로 남아있었거든요.\n상담사: 네.\n손님: 그래서 미납으로 결제를 했는데 지금 좀 전에 상담사분이 제 계좌로 연결해서 했는데 \n상담사: 네.\n손님: 그 그게 아직도 계속 미납으로 나오길래 어떻게 된 건지 확인 좀 할려고 전화드렸어요.\n상담사: 아 그러세요? 먼저 제가 조회를 해볼텐데 잠시 기다려주시겠습니까?\n상담사: 조회중으로 잠시만 더 기다려주시겠습니까?\n상담사: 네, 기다려주셔서 감사합니다. 확인해보니까? 오늘 납부하신 거는 ▲▲ 체크 카드 발급하면서 발생하시 발급 수수료 ▲▲원을 납부하신 거고요. 어 지금 남아 있는 ▲▲원은 ▲▲▲▲체크 카드 발급 ▲▲월 ▲▲일 발급 건으로 ▲▲ 카드를 만들 때 ▲▲원이 미납 돼 있다 해서 결제를 했는데요.\n손님: 아니 그건 알겠는데 그 앱상으로 들어가가지고 보면\n상담사: 네.\n손님: 계속 그 명세서라고 해서 확정 명세서라고 해 가지고\n손님:  ▲▲월 명세서에 계속 ▲▲원이라고 뜨고 ▲▲원이 미납됐다고 계속 떠 있어가지고\n상담사: 아 네, 손님 명세서는요. 이미 그 시점에 발생했던 금액을 수집해서 저희가 만들어드리는 거기 때문에요. 납부하신 정보가 반영이 되지는 않습니다.\n손님: 아 그래요? 그러면 지금 미납은 없고 결제 ▲▲원만 남은 거 맞죠?\n상담사: 어 네, 맞습니다.\n손님: 아 예, 알겠습니다.\n상담사: 네, 상담원 ▲▲▲이었습니다.",
		"consulting_time": "10:00"
	}
]