[
	{
		"source_id": "27019",
		"source": "하나카드",
		"consulting_date": "2025-09-06",
		"consulting_category": "가상 계좌 안내",
		"client_gender": "여자",
		"client_age": "30대",
		"consulting_turns": "34",
		"consulting_length": 344,
		"consulting_content": "상담사: 상담원 ▲▲▲입니다. 무엇을 도와드릴까요?\n손님: 아 네, 혹시 지금 미납 금액이 있는지 좀 확인해 주시겠어요? 잔액이 없어서 출금이 안 됐다가 일부만 또 나간 것 같거든요.\n상담사: 아 그러세요? ▲▲▲ 님 본인 맞으실까요?\n손님: 네, 네.\n상담사: 네, 지금 연체 금액이 ▲▲▲▲▲▲원 있는 걸로 확인되세요.\n손님: 아 그 언제까지 납부해야, 그 동일한 금액인 거예요?\n상담사: 이거는 바로 납부해 주셔도 괜찮거든요.\n손님: 그러니까 오늘이 지나면 또 연체료가 붙는 건가요?\n상담사: 네, 네 연체하시게 되면 수수료가 계속 붙으세요.\n손님: 이거를 그러면 통장에 제가 넣어놓으면 지금 출금되다가 ▲▲은행 계좌로 되어 있는데 거기에 제가 잔액을 입금해 놓으면 몇 시쯤에 빠져나가나요?\n상담사: 네, 시간은 정확하지 않으세요.\n손님: 네, 네.\n상담사: 저희 ▲▲은행 같은 경우에는 이제 실시간으로 출금되시는데 타행이다 보니까 4시 이전까지는 출금되실 건데 그 이후로는 이제 마감 시간이 있기 때문에 확답은 드릴 수 없어요.\n손님: 아 오늘 넣어놓으면 4시 이후에는 다 받는게 낫나요, 그러면?\n상담사: 아니요, 실제는 저희가 또 출금 요청을 하거든요, 시간 같은 경우는 이제 정확하지 않으세요.\n손님: 네, 네.\n손님: 아 그래요? 그러면 오늘 제가 넣어놓긴 할 건데 만약에 출금이 안 되면 가상 계좌로도 입금해도 되죠?\n상담사: 네, 가상 계좌로 입금해 주셔도 되고 안 그러면 바로 즉시 결제해 주셔도 괜찮으세요.\n손님: 아 제가 다른 계좌에서 한 번 이체해 놓으려고요, 출금되도록 해놓으려고 하거든요. \n상담사: 네.\n손님: 그래서 뭐 가상 계좌를 알려주시면 제가 출금되는지 확인하고 안 되면 그쪽으로 바로 입금할게요.\n상담사: 지금 가상 계좌를 알려달라고 하시는 말씀 맞으실까요?\n손님: 네, 네 그러니까 지금 가상 계좌를 알려주시면 제가 일단 그 출금 계좌에 돈을 입금해놓는데 오늘 4시에 4시나, 아니면 그 이후에 저녁에 입금되면 그냥 그대로 나가고 그냥 두면 지금 출금되는 거잖아요.\n상담사: 네, 맞습니다.\n손님: 네, 네 그런데 만약에 출금이 안 되면 제가 가상 계좌로 입금을 바로 할게요.\n상담사: 아 그러세요? 그 가상 계좌 같은 경우는 오늘 밤 11시 30분까지 입금해 주셔야 결제 처리되시고요. 이제 정확한 금액으로 해주셔야 처리가 되십니다.\n손님: 그럼 ▲▲▲▲▲원 이것을 정확하게 넣으면 되는 거죠?\n상담사: 네, 제가 이제 문자로 발송해 드릴 거고요, 유의사항은 문자로 받으실 수 있으니 해당 내용을 꼭 확인 후에 이용 부탁드리겠습니다. 그런데 안내해 드린 금액은 오늘 기준이라 만약에 납부가 안 되시면 금액이 달라집니다.\n손님: 네.\n상담사: 네, 네 그렇게 되면 저희 쪽으로 한 번 더 문의해 주시고 만약에 손님이 금액이 나간 거 확인하고 이 가상 계좌로 입금해 주시면 됩니다. \n손님: 아 네, 알겠습니다.\n상담사: 네, 지금 발송해 드리겠습니다.\n손님: 네.\n상담사: 네, 감사합니다. 상담원 ▲▲▲이었습니다.",
		"consulting_time": "09:30"
	}
]