[
	{
		"source_id": "24136",
		"source": "하나카드",
		"consulting_date": "2025-08-28",
		"consulting_category": "프리미엄 바우처 안내/발급",
		"client_gender": "여자",
		"client_age": "50대",
		"consulting_turns": "35",
		"consulting_length": 355,
		"consulting_content": "상담사: 상담원 ▲▲▲입니다.\n손님: 네, 저기 카드 발급받아서 그 바우처 신청을 하려 그러는데요.\n상담사: 아, 그러신가요? 우선 본인 확인 먼저 들어가겠습니다. 성함이 ▲▲▲ 님 본인 맞으십니까?\n손님: 네.\n상담사: 안녕하세요? ▲▲▲ 님 ▲▲카드를 이용해서 진심으로 감사드리겠고요. 혹시 이번에 신청하셨던 카드라고 하시면은 그 ▲▲▲▲▲▲ 말씀하시는 걸까요?\n손님: 맞아요.\n상담사: 네, 이 카드로 그 첫해 바우처는 카드 수령 후에 해당 카드로 ▲▲▲원 이상을 사용해야 신청이 가능하거든요.\n손님: 아, ▲▲▲원 이상 사용이요?\n상담사: 네, 첫 회 경우에는 그 조건이 충족이 돼야 바우처 신청하실 수 있는데 아직까지 ▲▲▲원 충족되지는 않아서 이용 후 요청을 해야 할 것 같습니다.\n손님: 근데 그거를 바우처를 제가 요청을 해야 되나요, 아니면 자동으로 발급이 되나요?\n상담사: 아, 요청하셔야 되는 거고요. 다섯 가지 중에 하나 선택하셔야 되기 때문에 금액 사용 후 연락 주셔서 바우처 신청하시면 저희가 신청 도움드리고 있습니다.\n손님: 아, 그래요? 이거 또한 같이 이게 연회비가 ▲▲▲원인가 ▲▲원으로 알고 있는데.\n상담사: 네.\n상담사: 연회비 ▲▲▲원인 카드고요.\n손님: 어 예, 그거는 이미 선결제가 된 거죠?\n상담사: 잠시 기다려 주시겠습니까?\n상담사: 기다려 주셔서 감사합니다. 이번 돌아오는 아, 지났던 ▲▲월 ▲▲일 결제 청구 해당 카드 연회비까지 포함은 되어있던 걸로 확인되었습니다.\n손님: 음, 그러면은 그 바우처가 연회비하고 이렇게 대피해서 지급하는게 아니라 해마다 그러면 제가 별도로 뭐 처럼 신청해야 되는거죠?\n상담사: 네, 별도 신청 필요하고요. 일단 이 경우에는 카드 발급 후 ▲▲▲원 이상 사용했을 때 신청이 가능하고요. \n상담사: 두 번째 경우에는 바우처 제공기간 직전 ▲년 간의 ▲▲▲원 이상 신청시 그 다음에 또 바우처 이용을 신청을 하실 수 있다 확인되고 있거든요.\n손님: 아, 그러면 제가 카드를 발급 받으면 뭐 저 ▲▲개월인가요? 이르면 내년 ▲▲월부터 ▲▲월인가요?\n상담사: 바우처 제공 기간은 카드 발급부터이기 때문에요. 지금 아무래도 손님께서 신청하셨던 기간 ▲▲월 달 신청하셨기 때문에요.\n손님: 네.\n상담사: 네, 보통 그 기간을 ▲▲월부터 그 다음에 ▲▲월까지 기간으로 보기 때문에요. 또 그 다음에 ▲▲월부터 ▲▲월까지인데 다음 ▲▲월 그 이제 이거 신청하실 수 있을 때 그 직전 ▲년 간의 사용 실적 제외한 매출이 다 빼고 ▲▲▲원이 체크 한 다음에 바우처 신청 도움드리고 있습니다.\n손님: 어떤 매출은 빼고요?\n상담사: 어, 실적에 포함시키지 않는 매출들이 있어서요.\n손님: 아, 그래요?\n상담사: 네.\n손님: 알겠습니다. 그부분은 제가 그러면 확인할게요.\n상담사: 네, 감사합니다.\n손님: ▲▲월까지이니까 ▲▲월 지나면 충족만 되면 ▲▲월 넘어서 그 바우처를 제가 유선으로 신청해야 된다는 거죠?\n상담사: 아무래도 좀 따로 저기 홈페이지나 이런 채널을 지금 아무래도 작업을 하고 있지는 않을까 싶기는 한데요, 현재 까지 공지된 부분 채널이 저희 쪽에 연락 주셔서 하시는 거라서요.\n손님: 예.\n손님: 알겠습니다. \n상담사: 네, 감사합니다. 상담원 ▲▲▲이었습니다.",
		"consulting_time": "16:00"
	}
]