[
	{
		"source_id": "25302",
		"source": "하나카드",
		"consulting_date": "2025-09-02",
		"consulting_category": "단기카드대출 안내/실행 ",
		"client_gender": "남자",
		"client_age": "50대",
		"consulting_turns": "43",
		"consulting_length": 399,
		"consulting_content": "상담사: 상담원 ▲▲▲입니다. \n손님: 예, 수고하십니다.\n상담사: 아 예, 감사합니다.\n손님: 예, 제가 현금 서비스를 받았는데요. \n상담사: 네.\n손님: 한 번 있잖아요, 제가 그걸 ▲▲▲▲▲원이 빠졌는데\n손님: 그 지금 다시 ▲▲▲▲▲원 받아 가지고 그 결제 할까 싶어가지고 전화를 드렸어요. \n상담사: 그러셨군요? 일단 실례지만 ▲▲▲ 님 본인분 맞으세요?\n손님: 예, 맞습니다.\n상담사: 확인 감사합니다. 아 현금 서비스 지금 현재 100만 원으로 이용을 하시겠다라는 걸까요?\n손님: 예.\n상담사: 아, 그럼 이용하려는 카드 번호 마지막 네 자리가 어떻게 됩니까?\n손님: ▲▲▲▲\n상담사: 예, 만약 이용하시면 저희 17.51% 연이율 적용 되며 오늘 이용한 금액은 청구 다음 달 결제일이 ▲▲일에 되는데 이제 주말 공휴일 부분으로 실 결제일 15일이고 결제 될 때\n상담사: 이자금액 175,100원 함께 청구되는데 괜찮으세요? \n손님: 예, 예.\n상담사: 아 예. 그럼 신청 위해서 에이알에스 연결해 드리면 카드 비밀번호 네 자리 입력 부탁드립니다.\n손님: 예.\n상담사: 네, 지금 현재 그리고 제가 휴대폰으로 문자를 하나 보내드렸는데 거기에는 인증 번호 말씀 부탁드립니다.\n손님: 네.\n손님: ▲▲▲▲\n상담사: 네, 신용 상태 개선되어 요건이 충족된 경우 금리 인하를 요구할 수 있으며 보이스 피싱 예방 관련 안내드리겠습니다. 혹시 고금리 대출을 받고 상환하시면 저금리 대출이 가능하다거나 금융감독원, 경찰청, 검찰청, 금융 회사 직원 사칭 연락\n상담사: 받으셨거나, 그리고 또는 어떤 이유로라도 수수료를 먼저 납부해야 한다는 요구를 받고 대출을 실행하시는 건 아니시죠?\n손님: 예, 아닙니다.\n상담사: 아 예, 그럼 지금 결제 계좌 ▲▲ 은행 계좌번호 끝에 ▲▲▲▲로 끝나는 계좌로 입금되는데요, 입출금 가능한 정상 계좌 맞으세요?\n손님: 예, 그게 번호가 어떻게 된다고요?\n상담사: ▲▲▲▲로 끝나는 계좌번호입니다.\n손님: 잠깐만, 확인해볼게요.\n상담사: 네.\n손님: 네, 그 계좌 맞아요.\n상담사: 네, 신청 완료 되어서 저희 해당 계좌로 입금 처리 진행이 되었는데요. 손님 저희 현금 서비스 이용 관련 유의 사항은 문자로도 받으실 수 있으니 내용 꼭 확인 후 이용 부탁드립니다.\n상담사: 네, 네.\n손님: 아, 거기에\n손님: 그 ▲▲▲▲▲원 입금 됐어요? \n상담사: 네, 입금 처리해 드렸어요.\n손님: 어, 거기 100만 원을 내가 일단 그 아까 그 달 거 좀 빼주세요.\n상담사: 그럼 오늘까지 이자 포함 940,080원 결제 계좌인 ▲▲ 은행에서 그대로 출금하면 될까요?\n손님: 네.\n손님: 예, 그걸로 좀 빼주세요. \n상담사: 아 예, 알겠습니다. 처리해드렸어요. 오늘 이용하신 현금 서비스 관련 유의 사항 문자로 갔으니 꼭 읽어 봐 주세요. 전부 처리되었습니다.\n손님: 예, 고맙습니다.\n상담사: 네, 상담원 ▲▲▲이었습니다. \n손님: 예. \n\t                                        \n\t                                        ",
		"consulting_time": "16:30"
	}
]