[
	{
		"source_id": "25345",
		"source": "하나카드",
		"consulting_date": "2025-09-02",
		"consulting_category": "결제일 안내/변경/취소",
		"client_gender": "남자",
		"client_age": "60대",
		"consulting_turns": "42",
		"consulting_length": 320,
		"consulting_content": "상담사: 카드 ▲▲▲입니다.\n손님: 예, 안녕하세요?\n상담사: 안녕하십니까?\n손님: 예, 그 카드 그 연체 때문에 전화드렸는데요.\n상담사: 아 그러실까요? 본인 확인 후에 관련 안내 마저 도와드리겠습니다. \n손님: 네.\n상담사: 손님 등록된 휴대폰 번호랑 생년월일 말씀 부탁드립니다.\n손님: 예, 저 ▲▲▲▲▲▲▲.\n손님: 그 저 핸드 저 뒷번호도 얘기해야 돼요?\n상담사: 네, 뒷번호까지 말씀 부탁드립니다.\n손님: ▲▲▲▲\n상담사: 아 네. 아 휴대폰 번호를 말씀을 해 주시겠습니까?\n손님: 예.\n손님: ▲▲▲▲▲▲▲▲▲▲▲\n상담사: 네, 손님 본인 성함 말씀 부탁드립니다.\n손님: ▲▲▲이요.\n상담사: 네, 결제 은행명 말씀 부탁드립니다.\n손님: 아, 저 ▲▲ 은행이에요.\n상담사: 아 네, 우선 소중한 정보 확인 감사합니다. 우선 손님께서 10일 날 기초수급 돈이 들어온다고 이야기를 해 주셨는데요.\n손님: 예, 예.\n상담사: 지금 현재 이미 연체로 잡혀있으신 금액이시기 때문에 우선 카드가 이용 정지가 되시게 되면은\n손님: 예, 그거는 상관없어요. 네.\n상담사: 네, ▲▲ 이요?\n손님: 예, 그 돈 10일 날 자동으로 들어오니까\n손님: 그런데 그렇게 인자 안 쓰니까, 참고하시라는 얘기지\n상담사: 그러시면은 뭐 아예 결제일의 변경을 요청하시는 걸까요?\n손님: 그렇죠. 15일날로 결제를 하든가 그래야죠.\n상담사: 그러시면은 우선 결제일은 변경을 저희가 15일 날짜로 변경처리를 도와드리겠습니다.\n손님: 예.\n상담사: 그러시게 되면 결제일 변경 후 60일 이내에는 재변경이 어려울 수 있는데 괜찮으십니까?\n손님: 예, 예. 예.\n상담사: 첫 번째 결제일은 9월 아 결제일을 15일로 변경하시게 되면 첫 번째 결제일은 9월 15일, 두 번째 결제일은 10월 15일이 되십니다.\n손님: 예.\n상담사: 결제일 변경해도 기존 이용 금액이 결제일에 청구 되지 않을 수 있으며 단기 카드 대출이나 자동 이체의 경우 이용 기간에 따라 두 달분이 청구될 수 있는데 괜찮으십니까?\n손님: 예, 예.\n상담사: 변경하신 결제일에 대한 이용 기간을 문자로 받아보실 수 있습니다. 해당 내용 꼭 이용 부탁드립니다. 그래서 손님께서 10일 날 연체 금액이 들어오신다고 하시게 되면 우선 카드는 정지가 그대로 되실 거기 때문에\n상담사: 되시더라도 그냥 체크 카드로 결제하시는 통장에 잔고 있으시면 결제는 문제는 없으시지만 후불 교통은 이용이 제한되는 점 참고 부탁드립니다. \n손님: 네.\n상담사: 15일 날, 이제 손님 15일 날\n상담사: 15일 날 그때 납부 해 주시면 되는 걸로 확인되십니다.\n손님: 예.\n상담사: 네, 상담원 ▲▲▲이었습니다.\n\t                                        ",
		"consulting_time": "16:30"
	}
]