[
	{
		"source_id": "26977",
		"source": "하나카드",
		"consulting_date": "2025-09-06",
		"consulting_category": "도난/분실 신청/해제",
		"client_gender": "남자",
		"client_age": "40대",
		"consulting_turns": "60",
		"consulting_length": 311,
		"consulting_content": "상담사: 상담원 ▲▲▲입니다.\n손님: 네, 그 분실 신고된 그 카드를 해지하려고 그러는데요.\n상담사: 네, 네.\n상담사: 카드 해지 말씀이십니까?\n손님: 아 예, 분실 신고 해제요.\n상담사: 아 분실 신고 해제요, 카드 찾으셨습니까?\n손님: 네, 네.\n상담사: 네, 소지하고 계실까요?\n손님: 네, 네. 그래서 지금\n상담사: 네, 제가 손님 정보 확인 후에 분실 해제를 도와드리겠습니다. 연락 주신 손님 휴대폰 번호가 어떻게 되실까요?\n손님: 네.\n손님: ▲▲▲▲▲▲▲▲▲▲▲요.\n상담사: 네, 생년월일이 어떻게 되실까요?\n손님: ▲▲년 ▲▲월 ▲▲일이요.\n상담사: 네, 연락 주신 손님 본인의 성함이 어떻게 되십니까?\n손님: ▲▲▲이요.\n상담사: 네, 마지막으로 결제 은행이 어떻게 되십니까?\n손님: ▲▲은행이요.\n상담사: 네, 소중한 정보 확인 감사합니다. \n상담사: 현재 2건 체크카드가 확인되고 있는데 둘 다 분실 해지하신 거 맞으실까요?\n손님: 네, 네 분실 해제 .\n상담사: 네, 먼저 분실 해제하실 카드 뒷자리 네 자리 말씀 부탁드리겠습니다.\n손님: 다 말씀드릴게요. 바로바로.\n상담사: 아 한 건, 한 건씩 진행할게요.\n손님: 어떤 걸로 될까요?\n상담사: 아무거나 말씀 주세요, 손님 편하신 걸로요.\n손님: ▲▲, ▲▲▲로\n상담사: 네, 이 카드로 먼저 진행하겠습니다.\n손님: 네.\n상담사: 아 손님 제가 그 문자로 인증번호를 보내드릴 거예요, 그 여섯 자리만 확인해 보시고 여섯 자리 말씀 부탁드리겠습니다.\n손님: 네, 네.\n상담사: 네, 발송했습니다.\n손님: 불러드릴게요.\n상담사: 네, 네.\n손님: ▲▲▲▲▲▲\n상담사: 네, 확인 감사합니다. 제가 다시 한번 에이알에스 연결하면 이 카드에 대한 비밀번호 있죠? 비밀번호 네 자리 입력을 부탁드리겠습니다. 연결하겠습니다.\n손님: 네.\n상담사: 네, 확인 감사합니다. 제가 지금 이 카드에 대해서 분실 해제하겠습니다.\n손님: 예, 또 다른 카드를 불러드릴까요?\n상담사: 아 잠시만 기다려 주시겠습니까?\n손님: 네.\n상담사: 예, 방금 거는 분실 해지되었습니다. 그리고 또 다른 카드를 가지고 계시죠?\n손님: 네, 네.\n상담사: 예, 그 카드에 대해서 다시 분실 해제 진행하겠습니다. 카드 번호 마지막 네 자리 말씀 부탁드리겠습니다.\n손님: 네.\n손님: ▲▲▲▲요.\n상담사: 네, 확인 감사합니다.\n상담사: 네, 이 건도 그 제가 에이알에스로 연결하면 카드 비밀번호 네 자리 입력 부탁드리겠습니다.\n손님: 네.\n상담사: 예, 잠시만 기다려 주시겠습니까?\n손님: 네.\n상담사: 예, 이것도 동일하게 제가 에이알에스로 연결하면 그 카드 비밀번호 네 자리 입력 부탁드리겠습니다.\n손님: 네.\n상담사: 네, 이것도 동일하게 카드 해제 진행하겠습니다. 분실 해제 진행하겠습니다.\n손님: 예.\n상담사: 예, 2건의 카드가 분실 해제가 돼서 오늘부터 이제 정상적으로 사용 가능하시고 그 후불 교통 기능은 평일 기준 오늘부터 2, 3일 후에 그때부터 사용 가능하십니다.\n손님: 아 네, 알겠습니다.\n상담사: 네, 저는 상담원 ▲▲▲이었습니다.\n손님: 네, 감사합니다.\n상담사: 네, 감사합니다.",
		"consulting_time": "14:30"
	}
]