[
	{
		"source_id": "24469",
		"source": "하나카드",
		"consulting_date": "2025-08-29",
		"consulting_category": "이용내역 안내 ",
		"client_gender": "여자",
		"client_age": "50대",
		"consulting_turns": "43",
		"consulting_length": 303,
		"consulting_content": "상담사: 상담원 ▲▲▲입니다.\n손님: 제가 아까 그 ▲▲시 ▲▲분에 빵집에서 쓴 거까지 다 ▲▲에 ▲▲▲▲▲▲원인데요.\n상담사: 네.\n손님: 그 저희가 금방 그 ▲▲▲원 기름을 넣었다가 다시 취소하고 ▲▲원만 긁었는데\n상담사: 네.\n손님: ▲▲▲▲▲▲원이 더 긁겨있어요. 뭐 때문에 그러는지 궁금해서요.\n상담사: ▲▲▲▲원이요?\n손님: 네, ▲▲▲▲원 차이가 나네요.\n상담사: 해당 계산 한번 해 드릴게요. 실례지만 연락주신 분 ▲▲▲ 님 본인분 맞으신가요?\n손님: 네.\n상담사: 그러면 일단은 저희가 ▲▲▲원 결제하시기 전에 누적 금액을 한 번 봐드릴게요.\n상담사: 이때 ▲▲▲원 사용하셨다가 누적 금액이 ▲▲▲▲▲원이고\n손님: 네.\n상담사: 그 다음에 ▲▲원 사용 되셨고\n상담사: 그러면 실제로 누적 금액이 ▲▲▲▲▲원이어야 되는데 차액이 조금 있다라는 말씀을 해주시는 거네요.\n손님: 네.\n손님: 거의 ▲▲▲원에도 지금 잔액이 나와 있어요.\n상담사: 일단은 저희가 중간에 뭔가 결제 내역 있으신지 한 번 더 확인을 한번 해볼 텐데 잠시만 기다려 주시겠어요?\n손님: 네, 네.\n상담사: 기다려 주셔서 감사합니다. 고객님 혹시 저희 ▲▲카드로 하셔서요. 교통 카드 사용하시죠?\n손님: 어\n손님: 네, 네.\n상담사: 확인해 보니깐 교통카드는 고객님 선불로 충전 이용하시는 게 아니라 후불 개념이잖아요? 그래서 ▲▲월 ▲▲일 오늘 날짜로 며칠동안 사용하셨던 교통비가 ▲▲▲원이 승인이 되었더라고요?\n손님: 네.\n손님: 제가\n손님: 그게 내가 나중에 후불로 한 번에 저기 되는 거 아닌가요?\n상담사: 네, 이거는 후불 개념이기 때문에요. 고객님 청구는 한 달에\n손님: 아 그러면 ▲▲▲▲원이 내가 ▲▲월 달에 쓴 게 ▲▲▲▲원이라는 얘기예요?\n상담사: 아니요, 고객님.\n상담사: 이거는 후불 개념이시기 때문에 저희가 고객님께 청구하는 거는 한 달에 한 번씩 청구를 할 거예요. 그런데 어떻게 보면 고객님의 신용 카드 한도는 후불 교통 카드로 사용하시는 거기 때문에 뭐 2, 3일에 한 번 3, 4일에 한 번\n상담사: 그 말씀하셨던 버스나 지하철 이용하실 때 그 데이터가 저희 쪽으로 넘어온 거예요. 그거는 데이터가 넘어오면 누적 금액 이렇게 플러스로 진행을 하고 대신 청구는 한 달에 한 번만 진행을 하는 거예요.\n손님: 네.\n손님: 아 그거구나\n손님: 이거는 4일에 한 번씩 계속 쓴 거를 누적으로 해서 합계를 한다는 얘기죠? 데이터가 넘어오면은.\n상담사: 예, 맞습니다. 고객님.\n손님: 아 그래요? 알겠습니다.\n상담사: 감사합니다. 혹시 마지막으로 저희 카드 대출 상담 가능하신데 안내 도와드릴까요?\n손님: 아니요. 아니요. 괜찮습니다.\n상담사: 네, 나중에 혹시라도 이용 어려우실 수 있는데 괜찮을까요?\n손님: 뭐가 어렵다고요?\n상담사: 대출이요, 고객님.\n손님: 아 대출 괜찮아요.\n상담사: 네, 상담사 ▲▲▲이었습니다.",
		"consulting_time": "15:00"
	}
]