[
	{
		"source_id": "22952",
		"source": "하나카드",
		"consulting_date": "2025-08-22",
		"consulting_category": "한도 안내",
		"client_gender": "여자",
		"client_age": "60대",
		"consulting_turns": "33",
		"consulting_length": 242,
		"consulting_content": "상담사: 상담원 ▲▲▲입니다.\n손님: 여보세요? 뭐 좀 문의 좀 할려 그러는데요. ▲▲ 한도 조정 가능할까요?\n상담사: 어, 해당 건 한번 조회해 드릴 텐데요. ▲▲▲ 님 본인 맞으십니까?\n손님: 네 네.\n상담사: 네. 손님분께서 현재 총 한도가 ▲▲▲▲▲원 있으시고, 현재까지 사용하신 한도가 ▲▲▲▲▲▲▲▲원이셔 가지고요. 잔여 한도는 ▲▲▲▲▲▲▲▲▲▲원 남으셨는데요. 여기에서 더 상향을 원하시는 걸까요?\n손님: 네.\n손님: 세금 낼려고 그랬는데 안 되더라고요.\n상담사: 아, 그러셨군요? 네. 지금 저희 일단은 확인해 보니까 손님께서 결제하시려는 금액이 ▲▲▲▲▲▲▲▲▲원이셔가지고 한도에서 조금 많기 때문에 지금 잔여 한도에서 조금 많게 되셨기 때문에\n상담사: 결제가 안 되셨던 거고요. 이거 저희 조회해보니까 손님분께서 지금 당장은 적정 한도 사용 중이셔가지고 사양이 좀 어렵다고 나오세요.\n손님: 아, 그래요?\n상담사: 그래서 내가 그래서 이럴 경우에는 손님은 결제일이 ▲▲일이신데 미리 그 ▲▲일 날 결제가 되셔야 되는 금액을 미리 결제하시는 방법도 있으세요.\n손님: 네.\n손님: 아, 그러면은 ▲▲월 ▲▲일 날 결제일이라고요?\n상담사: 네.\n손님: 아, 그래요? 금액이 얼마요?\n상담사: 그게 예전 방식인 금액같은 경우에는 ▲▲월 ▲▲일\n상담사: ▲▲일 그런데 ▲▲월 ▲▲일이 이번 달에는 소요일이시라서 실제적으로 ▲▲월 ▲▲일 날에 출금되실 텐데요. 그 예정 금액이 ▲▲▲▲▲▲▲▲▲▲▲▲원이세요.\n손님: 아, 그래요?\n상담사: 네 네.\n손님: 지금 그렇게 하면 예를 들어서 저기 그 금액은 들을 수 있는 거죠? 할 수 있는 거죠, 다른 금액은?\n상담사: 네. 일부만 일부만도 가능하세요.\n손님: 아, 카드요? ▲▲원짜리는 가능하잖아요.\n상담사: 네 네.\n손님: 그러면은 할부를 만약에 내가 이거를 할부로 저기 내면은 이번 달에 빠져나가나요?\n상담사: 아니요. 오늘 결제하시게 되면은 다음 달인 ▲▲월 달에 빠져 나가게 되시는 거죠.\n손님: 아, 오늘 이거를 할부를 내면?\n상담사: 네. 오늘 할부 넣으시면 ▲▲월 달부터 손님께서 할부로 하신 만큼에 개월수 만큼 빠져 나가신 가시는 거예요.\n손님: 그래요?\n상담사: 네.\n손님: 그래서 요거 하나만 해도 되죠?\n손님: 네, 알았습니다.\n상담사: 네. ▲▲카드 ▲▲▲이었습니다.\n손님: 네.",
		"consulting_time": "16:00"
	}
]