[
	{
		"source_id": "21062",
		"source": "하나카드",
		"consulting_date": "2025-08-09",
		"consulting_category": "선결제/즉시출금",
		"client_gender": "남자",
		"client_age": "30대",
		"consulting_turns": "39",
		"consulting_length": 377,
		"consulting_content": "상담사: 상담원 ▲▲▲입니다.\n손님: 아 예, 안녕하세요? 제가 며칠 전에 그 결제한 게 있는데요, 그 할부로.\n상담사: 네.\n손님: 그거 먼저 300만 원 결제했는데 한 100만 원 정도 선납하고 개월 수를 6개월로 바꾸려고 하거든요, 제가 개월 수 선택을 잘못해서. 12월로 했는데.\n상담사: 아 네, 그럼 ▲▲▲ 님 본인 맞으세요? \n손님: 예.\n상담사: 그럼 6개월로 변경해도 할부 수수료는 부과되는데 괜찮으세요? \n손님: 아 예, 6개월로 해주세요, 6개월로 해주시고.\n상담사: 6개월이요? \n손님: 예, 6개월로 해주시고 그 100만 원 먼저 그 금액이 100만 원 선납 가능하죠?\n상담사: 네, 그럼 제가 개월 수 먼저 변경하고 손님, 일부 선결제를 도와드릴 거고요, 지금 2월 3일에 쿠팡에서 300만 원 말씀하시는거 맞으세요? \n손님: 예, 맞아요.\n상담사: 네, 잠시만 기다려 주세요.\n손님: 예.\n상담사: 네, 기다려주셔서 감사합니다. 제가 6개월로 변경 처리해 드렸고 그럼 금액은 100만 원 정도 결제해 드릴까요? \n손님: 예, 그 금액에서 100만 원 결제해 주세요.\n상담사: 오늘 카드 할부 수수료 포함해서 1,001,523원이고요, 출금은 결제 계좌 ▲▲은행에서 해 드리면 될까요?\n손님: 예.\n상담사: 네, 남아 있는 원금은 남은 개월수 5개월로 나눠서 재청구되는 점, 참고해주시면 되고요. 네, 요청하신 금액 선결제 완료되었습니다.\n손님: 어 됐네요.\n상담사: 네.\n손님: 어 그러면 그게 얼마씩 나오죠, 한 달에 지금 남은 게 지금?\n상담사: 예, 보통 한 달에 청구되는 게 401,537원 조회되네요.\n손님: 이거 잠시만요, 아 맞네. 그럼 얼마 남아 있어요, 그 카드 금액이요? \n상담사: 지금 결제 예정 금액 1,879,000원으로 확인되십니다.\n손님: 1,879,000원이요? \n상담사: 네, 1,879,000원이요.\n손님: 아 그리고 제가 어제 결제한 곳 중에서 10만 원 따로 있지 않나요?\n상담사: 어제요? \n손님: 네.\n상담사: 잠시만 기다려 주세요. 지금 어제 쿠팡에서 10만 원이 조회됩니다.\n손님: 그것도 일시납 좀 해 주세요.\n상담사: 어 이거는 아직 승인 접수가 안 돼서 오늘은 선결제가 안 되세요.\n손님: 아 오늘 안 되나요?\n상담사: 네.\n손님: 알겠습니다. 감사합니다.\n상담사: 네, 감사합니다. 상담원 ▲▲▲이었습니다.\n손님: 예, 감사합니다. \n손님: 예.\n\t                                        \n\t                                        \n\t                                        ",
		"consulting_time": "09:30"
	}
]