[
	{
		"source_id": "24431",
		"source": "하나카드",
		"consulting_date": "2025-08-29",
		"consulting_category": "가상계좌 예약/취소",
		"client_gender": "여자",
		"client_age": "50대",
		"consulting_turns": "45",
		"consulting_length": 312,
		"consulting_content": "상담사: 상담원 ▲▲▲입니다. 무엇을 도와드릴까요?\n손님: 아 네, 수고하십니다. \n상담사: 네, 감사합니다.\n손님: 제가 좀 전에 저기 카드론 사용한 거 제가 가상계좌랑 금액을 문자로 부탁을 드렸는데 가상계좌 안내만 나와있고 금액이랑 가상계좌가 없어가지고요.\n상담사: 아 그러세요? 네, 실례지만▲▲▲님 본인분 되십니까?\n손님: 네, 네.\n상담사: 네, 확인 감사합니다. 그러면은 카드 그 장기 카드 대출 말씀하시는 거죠?\n손님: 예, 카드론 제가 사용한 거요.\n상담사: 네, 그럼 전액 상환하신다는 말씀이실까요?\n손님: 네, 네 네.\n상담사: 네, 그러면 가상계좌는 ▲▲은행으로 보내 드리면 될까요?\n손님: 네, 네.\n상담사: 네, 네 그럼 몇 가지 안내 사항 해드리겠습니다.\n상담사: 정확한 금액으로 입금하셔야 정상 처리되시고요.\n손님: 네.\n상담사: 네, 그리고 오늘 결제하시면 청구서 작업 전으로 돌아오는 결제일부터 매달 청구되는 금액이 변경이 되십니다. 그리고 미매입 건 후불 교통 카드 이용 금액 에스엠에스 수수료 자동 이체 이용 금액 있을 경우에 청구될 수 있으시고요. \n상담사: 가상계좌는 오늘 밤 11시 30분까지 입금하셔야 결제 처리가 되실 거고요.\n상담사: 추후 예약 없이 입금하실 경우 입금처리가 되지 않거나 환불 처리될 수 있으니 입출금이 가능한 정상 계좌인지 확인하시면 감사하겠습니다. 유의 사항은 문자로 받으실 수 있으니 해당 내역 꼭 확인하신 후 이용 하시길 바랍니다.\n손님: 예, 유의 사항은 제가 문자를 받았고요. 가상계좌랑 제가 오늘 입금해야 될 금액을 못 받았다고요, 문자요.\n상담사: 네, 그 금액 보내드릴게요. 혹시 금융 회사 금융 회사 직원이라는 전화나 문자를 받고 진행하시는 건 아니시죠?\n손님: 네.\n상담사: 네, 혹시 신용 등급 상향 대출 보증비 등의 수수료라며 면서 돈을 먼저 입금 입금하라고 한 건 아니시죠?\n손님: 네, 네.\n상담사: 네, 고금리 대출을 받고 상환하면 저금리로 대출이 가능하다고 한 건 아니시죠?\n손님: 네, 아닙니다.\n상담사: 네, 그러면 어 가상계좌 보내드렸습니다.\n손님: 금액은요?\n상담사: 어 가상계좌 이미 되어 있으신데요, 손님. 그러면 금액 안내해드릴게요. 메모 가능하십니까?\n손님: 네.\n손님: 네, 그 금액도 같이 넣어 주시는 거 아닌가요?\n상담사: 네, 그럼 문자로 발송해드리도록 하겠습니다.\n손님: 네, 네 문자를 발송해주시고 금액은 들을 수 없을까요?\n상담사: 네, 어떤 거 말씀하시는 건가요?\n손님: 상환할 수 있는 금액이요.\n상담사: 네, 그 금액 보내 드리도록 하겠습니다, 손님.\n손님: 네, 네 그 제가 금액을 지금 제가 좀 알 수 없냐고요? 문자는 보내주시고요.\n상담사: 네.\n상담사: 어 ▲▲▲▲▲▲▲원 이신데요.\n손님: 네, 네.\n상담사: 네, 그러면 보내드리도록 하겠습니다.\n손님: 네, 감사합니다.\n상담사: 네, 감사합니다. 상담사 ▲▲▲이었습니다.\n손님: 네.\n손님: 감사합니다.\n상담사: 감사합니다.",
		"consulting_time": "18:00"
	}
]