[
	{
		"source_id": "26032",
		"source": "하나카드",
		"consulting_date": "2025-09-04",
		"consulting_category": "이용내역 안내 ",
		"client_gender": "여자",
		"client_age": "50대",
		"consulting_turns": "56",
		"consulting_length": 368,
		"consulting_content": "상담사: 상담원 ▲▲▲입니다.\n손님: 네, 뭣 좀 문의 좀 드릴게요.\n상담사: 네.\n손님: 제가 ▲▲카드, 체크 카드가 없는데 계속 체크 카드가 계속 문자가 뜨네요. 이거 뭐 잘못된 거 아니에요?\n상담사: 아 그러세요? 많이 놀라셨을 텐데, 정보 먼저 확인해보겠습니다. 전화주신 ▲▲▲▲ 님 본인 맞습니까?\n상담사: 저희가 한 번 확인해보겠습니다. 잠시만 기다려 주겠습니까?\n손님: 네.\n상담사: 손님, 그러시면 핸드폰 번호 그러니까 ▲▲▲▲▲▲▲▲▲▲▲로 발송되는 거세요?\n손님: 네.\n상담사: 어, 저희가 한 번 확인해 볼 텐데, 잠시만 기다려 주시겠습니까?\n손님: 네.\n상담사: 네.\n상담사: 기다려 주셔서 감사합니다. 저희 ▲▲카드에서는 현재 지금 그 번호로 따로 문자가 한 거 없으시고, ▲▲▲▲▲▲▲번으로 발송이 된 거 맞으실까요?\n손님: 며칠 전에도 떠서 이게 뭐 잘못 했나 보다 그러고 있었거든요. 같은 날 2개가. 그저께인가?\n상담사: 네.\n손님: 그 ▲▲일 날인가, 2개가 뜨고 지금 또 떴어요.\n상담사: 저희 쪽에서는 지금 발송된 내역은 없으세요.\n손님: 잠깐만 기다려보세요. 잠깐만 기다려보세요.\n손님: 여보세요.\n상담사: 네.\n손님: 여기, ▲▲시 ▲▲분에 하나, ▲▲원 해갖고 체크 승인.\n손님: 무슨 내가 ▲▲▲원 ▲▲ 약국 이렇게 떴는데요.\n상담사: 저희 쪽은 따로 지금 이건 발송된 내역은 없으신 걸로 확인되고 있으세요. 그리고\n손님: 그런데 그러면 이게 문자가 잘못 됐다는건가요? 제 전화번호로.\n상담사: 어, 지금 저희 손님께서는 지금 사용하신 내역도 없는 걸로 확인되고 있고 ▲▲▲▲▲▲▲▲▲▲로 은거 맞으세요?\n손님: 네, 지금 제가 전화 걸고 있잖아요, 지금 문자 온 거 보고 지금 읽어 드렸잖아요.\n상담사: 저희쪽에서는 지금 발송된 내역 없는 걸로 확인되고 있으세요.\n손님: 그러면 이거 신경 안 써도 되는 거죠?\n상담사: 네, 그렇습니다.\n손님: 아 예. 알겠습니다. 아니 계속 뜨니까.\n상담사: 네, 아 네.\n손님: 이해가 안 가네, 왜 이 번호로 뜨지?\n상담사: 그러세요?\n손님: 더군다나 제 이름 앞에 ▲▲▲ 님 이게 온 거 보면은 제 이름이거든요?\n상담사: 네.\n손님: 잠시만 기다려보세요. 다시 한번 확인할게요.\n상담사: 네, 기다리겠습니다.\n손님: ▲▲▲에서 왔고, ▲▲▲에서 왔고, ▲▲▲▲▲▲▲ 지점 거기서도 오고\n손님: 계속 문자가 뜨고 있거든요, 그러면 이거 신경 안 써도 되는 거죠?\n상담사: 네, 지금 손님께서는 지금 그 번호는요, 저희 따로 발송된 건 없으신 걸로 확인되고 있으세요. 제가 ▲▲원 이상 건만 발송되는 걸로 확인되고 있으시고요.\n손님: 그런데, 지금 잠시만요.\n상담사: 네, 기다리겠습니다.\n손님: ▲▲원짜리가 떴고 ▲▲원짜리 것도 떴고 오늘 ▲▲▲원 짜리가 떴는데.\n상담사: 음.\n손님: 체크카드거든요? 이게 저는 신용 카드는 발급 받았는데, 안 쓴 지 너무 오래 됐고 체크 카드 자체가 없거든요?\n상담사: 어, 손님께 체크 카드 있으신데, 지금.\n손님: 제가 있어요? 체크 카드가?\n상담사: 네, ▲▲▲▲ 체크 카드가 있으신데, 사용하신 내역은 없으신 거구요, 지금 현재로써는.\n손님: 그러니까, 통장에 잔고도 없어서?\n상담사: 네.\n손님: 그래도 ▲▲ 은행은 안 하고 있는데 이게 뜨니까, 이상해서 전화 한번 드려요. 그러면 이거 신경 안 써도 되는 거죠?\n상담사: 네, 그렇습니다.\n손님: 예, 알겠습니다.\n상담사: 상담원 ▲▲▲이었습니다. \n손님: 네, 감사합니다.\n상담사: 네, 감사합니다.",
		"consulting_time": "18:00"
	}
]