[
	{
		"source_id": "25116",
		"source": "하나카드",
		"consulting_date": "2025-09-01",
		"consulting_category": "연체대금 안내 ",
		"client_gender": "남자",
		"client_age": "60대",
		"consulting_turns": "48",
		"consulting_length": 371,
		"consulting_content": "상담사: 상담원 ▲▲▲입니다.\n손님: 지금 뭐 그 다 인출해 가라고 연락드렸어요.\n상담사: 아 그러셨군요. 알겠습니다. 확인해서 처리하겠습니다. \n손님: 예, 그리고 인제 하시고 나서 지금 잠깐 뭐 하나 물어볼려고요.\n상담사: 네, 어떤 내용이실까요?\n손님: 인출 먼저 해주세요.\n상담사: 알겠습니다. ▲▲▲ 님 본인분 맞으시고요?\n손님: 네.\n상담사: 네, ▲▲▲▲▲▲원입니다. 인출 이후 잔고 있으면 이중출금될 수 있습니다. 이중인출 원치 않으시면 오늘 하루 결제계좌 잔고 비워주셔야 되며 이중 인출되더라도 내일 오전에 정상 환불처리됩니다.\n손님: 네.\n상담사: 완료되었고요, 어떤 내용이 궁금하실까요?\n손님: 그 뭐죠, 지금 여기 ▲▲카드가 제가 인제 ▲▲ 쓰고 있어서 ▲▲카드라고 해 가지고 그 쓴 거에 대해서 몇 프로 할인해 주고 하는지 최종 지금 이번에 할인된 금액이 얼마예요?\n상담사: 네, 조회 중에 있습니다.\n손님: 네.\n상담사: 청구서로 확인해 보니 ▲▲▲원을 할인받아보셨네요.\n손님: ▲▲\n상담사: ▲▲▲▲원이요.\n상담사: 네, 네.\n손님: 어떻게 어떤 식으로 그게 할인이 되는 거죠?\n상담사: 할인되는 금액은 저희가 확인해서 말씀드릴 텐데 잠시만 기다려 주시겠습니까?\n손님: 네.\n상담사: 네, 기다려 주셔서 감사합니다. 일단 실적을 얼마를 충족을 했느냐에 따라서 할인 금액이 틀려지는데요. 전달에 ▲▲▲원 이상 실적 충족 시 ▲▲원, ▲▲▲원 이상 충족 시 ▲▲원, ▲▲▲▲원 이상 충족 시 ▲▲원 할인이 되며 \n상담사: 오토 정기결제는 10%, 일반결제는 3% 할인을 받아볼 수 있는 카드세요.\n손님: 오토 내가 두 번 했는데 2개를 했는데\n상담사: 네, ▲▲▲씩 할인이 되는 거는 맞습니다만 실적 충족을 했을 때 한 달에 할인받을 수 있는 고객님 아까 말씀을 ▲▲▲원 이상이 돼 있잖아요, ▲▲▲원 이상일 때 ▲▲원, ▲▲▲▲원 이상일 때 ▲▲원이고요.\n상담사: 아니 그 이게 실적 충족을 못 했다라고 하면\n상담사: 0.5% 전 가맹점 할인되는 금액이 되어 있기 때문에 금액으로 해서 할인을 받아볼 수 있으세요.\n손님: 그러면 보통 ▲▲▲원 정도 이상은 만들어야 되는 거네요.\n상담사: 네, 못해도 이전 달에 실적으로 ▲▲▲원이나 ▲▲▲원 이상 충족을 하시고 할인을 받았습니다.\n손님: 아 이게 한 달\n상담사: 네, 전달 ▲▲일부터 말일까지 실적을 확인합니다.\n손님: 일단 한 번 전달 해야지 그 다음 달 혜택을 보는 거예요? \n상담사: 네, 맞아요. 두 가지 못하게 되면 전 가맹점 0.5% 할인 혜택이 있어서 혜택으로 할인을 받게 됩니다.\n손님: 예.\n손님: 아 이거를 처음에 이용을 몰르니깐 쓴 적이 없는데\n손님: 오래간만에 잘 알았습니다. 고맙습니다.\n상담사: 네.\n손님: 그 모르겠네, 내가 얼핏 보면. 그냥 그거 저기 이거 할인 내역을 제 메일로 보낼 수 있어요?\n상담사: 네, 네.\n상담사: 청구서를 다시 한번 이메일로 발송할까요?\n손님: 네, 그 할인 내역 제가 조회한 거는 알고 싶은데 어떻게 할인되는 거라고\n상담사: 아 청구서에 이용한 금액과 할인 받은 금액, 입금할 금액이 같이 기재가 되어 있거든요. 청구서 ▲▲▲▲▲▲으로 발송하면 될까요?\n손님: 아 맞아요. 예.\n상담사: 이제 받아보시는데는 시간 30분 정도 소요 될 수 있습니다.\n손님: 알겠습니다.\n상담사: 네, 감사합니다.\n손님: 네, 수고하세요.\n상담사: 네, 감사합니다.",
		"consulting_time": "12:30"
	}
]