[
	{
		"source_id": "24268",
		"source": "하나카드",
		"consulting_date": "2025-08-28",
		"consulting_category": "한도상향 접수/처리 ",
		"client_gender": "남자",
		"client_age": "40대",
		"consulting_turns": "39",
		"consulting_length": 427,
		"consulting_content": "상담사: 상담원 ▲▲▲입니다. 무엇을 도와드릴까요?\n손님: 네, 안녕하세요? 그 다름이 아니고요.\n상담사: 네.\n손님: 예, 한도를 좀 많이 늘리고 싶으면 어떻게 해야 되나요?\n상담사: 일단은 한도가 있으시면 일단 심사도 필요할 수 있는데요. 그 전화 주신 ▲▲▲ 님 본인 맞으시죠?\n손님: 네, 맞습니다.\n상담사: 네, 오랫동안 ▲▲카드 이용 감사드리겠습니다. 지금 총 한도와 ▲▲▲원이신데 지금 있다 우리 승인한도가 바로 보이지는 않아서 혹시 심사 진행을 좀 도와드릴까요? 손님.\n손님: 아 예, 그래서 심사 해 주시고 제가 지금 재직 증명서나 소득 증명 작년 소득 증명서가 있거든요.\n상담사: 예, 예.\n상담사: 요새는 소득은 안 받고요, 손님. 저희가 간단히 몇 가지 안내드리고 진행을 좀 해 드릴 건데요, 그 원하시면 한도가 얼마 얼마 정도 실까요? 손님.\n손님: 지금 한\n손님: 얼마까지 가능한 거예요?\n상담사: 저희가 따로 뭐 최대치가 있는 건 아니고 말씀해 주신 금액 그 일단 최대한 올려드리겠습니다. 손님 원하시는 금액 말씀하시면 됩니다.\n손님: 예.\n손님: 3,000,000원까지 가능한가요?\n상담사: 일단 접수해 드릴게요. 손님 총 한도 3,000,000원 해 드리고 그 현금 쓸 수는 기존에 ▲▲▲▲원이셨습니다. 이거는 그대로 진행해 드릴까요? 손님.\n손님: 네, 네.\n손님: 아, 이거는 줄일 수 있나요?\n상담사: 예, 상관없습니다. 일단은 한도 심사를 받으시고요. 그 줄이시는 건 언제든 가능하시기 때문에 고객님 필요하실 때 연락 주셔서 사용 조정하시면 돼요.\n손님: 아 네. 카드 한도만 3,000,000원까지 한번 늘려주세요.\n상담사: 일단 진행해 드릴게요. 그다음에 심사 중에는 손님의 신용 정보 필요할 수 있습니다. 이 부분 동의해 주시겠습니까?\n손님: 네, 네.\n상담사: 네, 그리고 요새는 서류 따로 안 받고요, 손님. 공공 마이데이터 서비스 동의하시게 되면요, 저희가 실시간으로 소득 서류 확인이 가능하십니다.\n손님: 아, 전 마이 데이터는 안 하겠습니다.\n상담사: 아, 손님 이거는 따로 안 하시겠다는 건가요?\n손님: 네, 네.\n손님: 마이 데이터는 안 할게요.\n상담사: 안 하시겠습니다. 알겠습니다. 손님 그러면 그 소득 증빙 자료 일단 저희가 뭐 재직 증명서는 안 해 주셔도 되고 그다음에 소득금액증명원 혹시 발송 가능하실까요?\n손님: 네, 네. 팩스 번호 알려주시면 같이 보내드리겠습니다.\n상담사: 아, 알겠습니다. 그러면 일단 서류 받는 걸로 했으면 하겠습니다. 특수 번호는 제가 일단 문자로 남겨드릴 거고요, 손님.\n손님: 네, 네.\n상담사: 그리고 저희가 손님 뭐 따로 손님 명의의 부동산이 있으시면 제가 기재해 드릴까요?\n손님: 아니요, 괜찮습니다.\n상담사: 아, 괜찮으시고 알겠습니다. 그다음에 저 결과는 미리 확답은 드리기 어렵지만 평일도 하루 이틀정도 시간 양해 부탁 드리고 나니 결과는 심사팀에서 이제 알림 톡이나 문자로 전송해 드리니까 꼭 결과 확인 부탁드리고요.\n손님: 네, 알겠습니다.\n상담사: 네, 팩스번호 바로 문자드리고 심사 바로 올리겠습니다.\n손님: 네, 네.\n상담사: 감사합니다. 상담원 ▲▲▲이었습니다. \n손님: 네, 감사합니다.\n\t                                        \n\t                                        ",
		"consulting_time": "09:30"
	}
]