[
	{
		"source_id": "25176",
		"source": "하나카드",
		"consulting_date": "2025-09-01",
		"consulting_category": "결제일 안내/변경/취소",
		"client_gender": "남자",
		"client_age": "60대",
		"consulting_turns": "40",
		"consulting_length": 314,
		"consulting_content": "상담사: 상담원 ▲▲▲입니다.\n손님: 네, 수고하십니다. 저기 이제 카드를 뭐 그 핸드폰 하면서 카드를 만들었거든요. \n상담사: 네.\n손님: 저기 연계해가지고 카드 왔는데 이거 등록해야 되나요?\n상담사: 아, 그러세요? 그러시면 저희 쪽에 지금 확인했을 때 ▲▲카드 받으셨다고 하셨는데, 이 카드는 따로 사용 등록 없이 본인께서 직접 받으셨기 때문에 사용하셔도 됩니다.\n손님: 네, 네.\n손님: 아, ▲▲카드 바로 사용을 해도 된다는 건가요?\n상담사: 네.\n손님: 예, 잠깐만요. 그러면 이게 이제 뭐 ▲▲▲원 한 달에 쓰라 그랬잖아요? \n상담사: 네, 맞습니다.\n손님: 아, 이거를 언제부터 저 들어가는가요? 다음 달로 가져가나?\n상담사: 지금 확인했을 때, 손님께서 만드신 날짜는 ▲▲월이잖아요? \n상담사: 그래서 ▲▲월하고 ▲▲월은 실적 없이도 할인이 되는 기간이긴 합니다만, ▲▲월 달에 할인을 받으시려면 ▲▲월에 사용하셔야 됩니다.\n손님: ▲▲월 달부터 사용이라는 게, ▲▲월 ▲▲부터.\n상담사: 네, ▲▲월 ▲▲부터 말일까지는 사용을 하셔야 ▲▲월 달에 할인 가능합니다.\n손님: 아, 그리고, 한번씩 결제가 ▲▲, ▲▲일입니까?\n상담사: 결제일은 ▲▲일로 확인됩니다.\n손님: 네, ▲▲일 같으면, 어 전달 ▲▲부터 ▲▲일까지죠?\n상담사: 아니요, 아니요. 그건 ▲▲일입니다.\n손님: 아, ▲▲일까지?\n상담사: 네, ▲▲일이 확인했을 때 전월 ▲▲부터 말일입니다. ▲▲일로 변경을 해 드릴까요?\n손님: 예, 그러면 제가 지금 ▲▲일 날 결제일인데, ▲▲일이 그러면 전달 ▲▲일부터, ▲▲일부터 ▲▲일까지 저 ▲▲일까지?\n상담사: 네, 맞습니다. 네. 네.\n손님: 예, 그럼 ▲▲일 날 좀 해지해 줄 수 있나요?\n상담사: 네, 그러시면 변경 후 60일 이내에는 재변경이 어려울 수 있는데 괜찮으십니까?\n손님: 예?\n상담사: 변경하시고 60일 이내에는 재변경이 어려울 수 있는데 괜찮으십니까?\n손님: 예, 예. 한 달 다거나 그렇게 해주세요.\n상담사: 네, ▲▲일로 변경하면 ▲▲월 ▲▲일, 월 ▲▲일로 청구되고요. 결제일 변경해도 기존 이용 금액이 변경 후 결제일에 청구 되지 않을 수 있고, 단기 카드 대출이나 자동이체의 경우 이용 기간에 따라 두 달분이 청구될 수 있는데 괜찮으세요?\n손님: 네.\n상담사: 네, 그러시면 변경하신 결제일에 대한 이용 기간에 문자로 발송해 드리니까 내용 확인하시고 이용하세요.\n손님: 예, 그러면 이게 저 지금 ▲▲월 ▲▲일 날 지금 나온다는 거 아니에요, 그렇죠?\n상담사: 네, 맞습니다.\n손님: 그런데 ▲▲월 ▲▲일 쓴 게 ▲▲월 거라면 쓴 게 없잖아요. ▲▲월 달 거는 안 들어간다고 그랬잖아요. ▲▲월달부터 서 그 실적이 들어간다는 건데.\n상담사: 네, 사용하시면 돼요. 올해 ▲▲월 ▲▲일부터 말일까지 사용하시면 됩니다.\n손님: 그러니까 ▲▲월 달에는 뭐 관계없다는 거죠?\n상담사: 네, 맞습니다.\n손님: 알겠습니다.\n상담사: 네, 상담원 ▲▲▲이었습니다.\n손님: 네.",
		"consulting_time": "15:00"
	}
]