[
	{
		"source_id": "26844",
		"source": "하나카드",
		"consulting_date": "2025-09-05",
		"consulting_category": "도난/분실 신청/해제",
		"client_gender": "남자",
		"client_age": "40대",
		"consulting_turns": "48",
		"consulting_length": 277,
		"consulting_content": "상담사: ▲▲카드 ▲▲▲입니다.\n손님: 네, 수고하십니다. 제가 카드 재발급 신청을 해서요, 신용.\n상담사: 네, 손님.\n손님: 네, 그 전에 걸 놓고 새로 받았는데\n상담사: 네.\n손님: 그럼 그 카드 비밀번호가 똑같을 텐데 카드비밀번호 등록\n상담사: 네.\n손님: 다르다고 그래가지고\n상담사: 음 확인해드릴게요. 카드 소지하고 계시는 건가요?\n손님: 네.\n상담사: 몇 가지만 여쭙겠습니다. 생년월일과 휴대폰 번호 어떻게 되세요?\n손님: 생년월일 ▲▲▲▲▲▲▲요.\n상담사: 네.\n손님: 휴대폰 번호는 ▲▲▲▲▲▲▲에 ▲▲▲▲번이요.\n상담사: 전화 주신 손님 본인 성함 어떻게 되십니까?\n손님: ▲▲입니다.\n상담사: 결제 은행 어느 은행이세요?\n손님: ▲▲은행입니다.\n상담사: 확인 감사드리고요, 카드 번호 마지막 네 자리 어떻게 되세요?\n손님: ▲▲▲▲▲▲▲요.\n상담사: 아 감사드립니다. 지금 보니까 아마 손님께서 재발급을 하고 나서 분실 신고를 하셨기 때문에 카드가 정상 카드가 아닙니다. 그래서 제가 지금 바로 분실 해지 할 거예요. 잠시만 기다려 주시겠습니까?\n손님: 어\n손님: 예. \n상담사: 기다려 주셔서 감사드립니다. 손님 휴대폰으로 인증번호라고 해서 문자 하나 발송해드렸어요. 확인 부탁드릴게요.\n손님: 네.\n손님: 어 번호 말씀드리면 되나요?\n손님: ▲▲▲▲▲▲▲이요.\n상담사: 네, 확인해드려볼게요. 비밀번호도 한 번만 입력해봐 주세요.\n손님: 네.\n상담사: 우선 지금 확인해 보니까 손님 비밀번호가 일치하지 않는 걸로 확인돼요. 비밀번호도 한 번 더 변경해드려야 될 거 같습니다. 제가 에이알에스 연결해 드릴 거예요.\n손님: 네.\n상담사: 그럼 앞으로 사용하시고자 하는 비밀번호 네 자리 입력해 주시면 되구요, 또 한 번은 카드 뒷면에 서명하는 곳에 끝에 세 자리 숫자를 누르라고 나갈 거예요.\n손님: 네.\n상담사: 차례로 연결 한번 해 볼게요.\n손님: 네.\n상담사: 비밀번호를 변경했기 때문에 이 번호로 이용하시면 되고요, 카드 정상으로 이용할 수 있도록 해지 할게요. \n손님: 저 이 카드로 그 뭐지, 현금 서비스\n손님: 그 뭐지,\n손님: 씨디기에서 돈을 찾을 수 있는 거 맞죠?\n상담사: 어 네, 카드는 인출 기능 있습니다.\n손님: 아 그래요? 알겠습니다.\n상담사: 네, 카드도 정상으로 처리해 놨기 때문에 이용하실 수는 있고요, 완료되었습니다.\n손님: 네.\n손님: 전에 쓰는 카드는 그냥 없애면 되는 건가요?\n상담사: 어 맞아요. 이제 카드 사용 등록까지 지금 완료가 된 거기 때문에 기존 카드는 자동으로 해지가 됐어요. 그냥 잘라서 폐기하시고 그냥 새 카드 이용하시면 돼요.\n손님: 네, 고맙습니다.\n상담사: 감사합니다. 상담원 ▲▲이었습니다.\n손님: 네.",
		"consulting_time": "17:30"
	}
]