[
	{
		"source_id": "23190",
		"source": "하나카드",
		"consulting_date": "2025-08-23",
		"consulting_category": "입금내역 안내",
		"client_gender": "남자",
		"client_age": "50대",
		"consulting_turns": "31",
		"consulting_length": 306,
		"consulting_content": "상담사: 상담원 ▲▲▲입니다.\n손님: 여보세요?\n손님: 아 예, 수고 많습니다. 카드 대금이\n손님: 이중 출금된 것 같아서 확인 좀 할게요.\n상담사: 아 네. 알겠습니다. ▲▲▲ 님 본인 맞으세요?\n손님: 네.\n상담사: 잠시 기다려주시겠습니까?\n손님: 네.\n상담사: 손님, 혹시 이중 출금됐다고 하신 부분이 그 ▲▲은행 손님 오늘 ▲▲일 날짜 결제 대금 말씀하시는 거 맞으세요?\n손님: 예.\n상담사: 잠시만 기다려주세요. 한 번 더 좀 확인해 보겠습니다.\n손님: 예.\n상담사: 손님 기다려주셔서 감사합니다. 이중 출금이 우선, 된 거는 없어요. 원래 청구되는 지금 본인 되었 님의 카드 대금이\n상담사: 삼백만 원이었는데요.\n손님: 네.\n상담사: ▲▲은행 결제 계좌에서 오늘 새벽 4시 30 분과 6시 20분에 두 번 나눠서 이백오십만 원이 자동 인출이 되었고, 이후에 오십만 원을 나머지 금액을 결제를 하신 거예요.\n손님: 아, 나머지 했고.\n상담사: 네, 그래서 초과로 결제하신 금액은 없어요.\n손님: 아, 그러면 이제 없죠?\n손님: 어 그 뭐야, 아 내가 잘못 알고 있어요.\n상담사: 오늘 납부하실 금액은 다 처리를 하셨어요.\n손님: 아, 그러면 뭐 미납된 거는 없죠?\n상담사: 예, 그런 건 아니고요. 이제 ▲▲은행이다 보니깐은 저희가 오전 중으로 출금됐던 금액이 있었고 그거를 뺀 나머지 금액을 결제를 하신 걸로 보시면 돼서요. 이중으로 출금을 하신 건 없어요.\n손님: 네.\n상담사: 예, 없고 지금은 손님 ▲▲은행 쪽 계좌로도 오늘도 추가로 결제하실 금액은 없고 이제 가족 카드 쪽에 이제 우체국으로 연결된 계좌에서 100,000원만 이제 결제가 될 예정이세요.\n손님: 아, 가족 카드 그게 ▲▲▲▲원 이렇게 결제를 해야 되는데 미납돼 있다고요?\n상담사: 아니요, 그거 그니까 그 가족카드 ▲▲▲▲원도 오늘 결제일이시거든요.\n손님: 아 예. 예.\n상담사: 그래서 그것만 오후 ▲▲시전까지 우체국에다가 입금해 놓으시면 되겠습니다.\n손님: 아 알겠습니다. 예.\n상담사: 네, 상담원 ▲▲▲이었습니다. 좋은 하루 보내세요.\n\t                                        \n\t                                        ",
		"consulting_time": "15:00"
	}
]