[
	{
		"source_id": "200249",
		"source": "하나카드",
		"consulting_date": "2025-08-03",
		"consulting_category": "도난/분실 신청/해제",
		"client_gender": "여자",
		"client_age": "20대",
		"consulting_turns": "50",
		"consulting_length": 320,
		"consulting_content": "상담사: ▲▲카드 상담원 ▲▲▲입니다. 무엇을 도와드릴까요? \n손님: 아 네, 안녕하세요? 혹시\n상담사: 네, 안녕하세요? \n손님: 휴대폰도 그 저 이 카드를 재발급 좀 받으려고 그러는데요.\n상담사: 네. \n손님: 하는 중이여서\n상담사: 재발급 원하셨는데요. 고객님 본인 확인부터 하겠습니다. ▲▲▲ 고객님 본인 맞으신가요? \n손님: 네 네.\n상담사: 네, 체크 카드 재발급을 원하신다고 하셨는데 재발급 사유가 어떻게 되실까요? \n손님: 아 잃어버려서요. \n상담사: 분실하셨다는 말씀이시죠? 그러면 분실 재발급으로 도와드릴 수 있거든요.\n손님: 네 네.\n상담사: 예, 분실 신고부터 진행될 텐데요. 고객님 카드를 잃어버린 날짜, 시간, 장소를 알고 계실까요? \n손님: 어 아니오.\n상담사: 어 네, 그러면\n상담사: 분실 장소는 모름, 분실 일자는 오늘 날짜로 기재하는 걸 도와드려도 되겠습니까? \n손님: 네 네 네.\n상담사: 네, 알겠습니다. 잠시만 기다려 주시겠습니까? 모바일 카드도 같이 등록되시기 때문에요, 카드는 더 이상 사용되지 않으세요. 그 점 참고 부탁드리면서요. 분실 재발급이시기 때문에 한 번 등록 후 재발급 처리까지 진행될 텐데요. 잠시만 더 기다려 주시겠습니까? \n손님: 네. \n손님: 혹시 재발급 비용도 있나요? \n상담사: 일단 재발급 비용은 따로 확인되지 않으시는데 ▲▲원이 부과되실 수도 있으세요.\n손님: 아 ▲▲원이요? 아 네 네.\n상담사: 예. \n상담사: 네, 그 점 참고 부탁드리면서요, 분실 재발급 시 고객님께서는 카드를 찾으셔도 재발급 취소가 어려울 수 있는데 괜찮으실까요? \n손님: 네 네.\n상담사: 네, 그러면 재발급 처리할 텐데요. 먼저 고객님 카드는 영업일 기준 5일 정도 소요되고 배송되세요.\n손님: 예. \n상담사: 네, 그다음에 그 자택에서 받아보실 건가요, 직장에서 받아보실 건가요? \n손님: 어 자택이요. 혹시 일주일 넘게 걸릴까요? \n상담사: 예. \n상담사: 5일을 넘는 경우가 없는데 평일 기준으로 5일이기 때문에요.\n손님: 네 네.\n상담사: ▲▲월 ▲▲일 중으로 확인되고 있어요. \n손님: ▲▲월 ▲▲일이요. \n상담사: 네. \n손님: 아 진짜요? \n손님: 아 혹시 다시 한번 연락드려도 될까요, 제가? \n상담사: 뭐 그럼 분실 등록은 되어 있기 때문에 그 상태 그대로 놔두실까요? \n손님: 아 네 네 네 네.\n상담사: 네, 알겠습니다. 그러면 네.\n손님: 혹시 그러면 기존에 안에 있던 돈들은 그대로 유지는되는 건가요? \n상담사: 네, 그대로 유지되십니다.\n손님: 아 네 네, 그럼 거기서 이제 재발급 받으면 되는 거죠? \n상담사: 네 네.\n손님: 아 네 네, 알겠습니다. 일단 수리만 해 주세요.\n상담사: 아 네, 그럼\n상담사: 네, 분실 신고하고 재발급은 보류하신다는 말씀 맞으시죠? \n손님: 네 네, 맞아요.\n상담사: 네, 감사합니다. ▲▲카드 상담사 ▲▲▲이었습니다.\n손님: 네. ",
		"consulting_time": "11:30"
	}
]