[
	{
		"source_id": "21141",
		"source": "하나카드",
		"consulting_date": "2025-08-09",
		"consulting_category": "결제일 안내/변경 ",
		"client_gender": "남자",
		"client_age": "60대",
		"consulting_turns": "20",
		"consulting_length": 238,
		"consulting_content": "상담사: 카드 브이아이피 상담사 ▲▲▲입니다. 무엇을 도와드릴까요?\n손님: 예, 제가 급여일이 변경돼서 잠시만 애플리케이션으로 그 결제일을 25일로 변경했는데 반영되어 있나 좀 봐주세요. 아직 앱에서는 반영이 안 돼 있는 것 같아서요. \n상담사: 네, 잠시 확인해 드리겠습니다. 전화 주신 분은 실례지만 ▲▲▲ 고객님 본인 맞으세요? \n손님: 예, 맞습니다.\n상담사: 네, 감사합니다. 일단 25일 변경 이력은, 접수된 이력은 확인되시고요, 그럼 오늘은 10월 25일 그대로이고 이달 10월 10일에 또 결제를 한 번 더 했습니다.\n손님: 예, 그렇죠.\n상담사: 네, 그래서 이달은 10월 10일과, 10월 25일, 이렇게 하시면 되는 거고요, 변경되어 있습니다. \n손님: 아 그러면 예, 알겠습니다. 그럼 반영이 되는 거죠?\n상담사: 예, 감사합니다. 네, 이달 10월 25일에 또 납부해주시면 됩니다.\n손님: 예, 그러면 애플 앱에, ▲▲카드 앱에도 오늘 그러면 변경됐으니까 결제 금액이 또 달라집니까, 10월 25일 거? \n상담사: 네, 내일 이후에 이제 10월 청구 작업일을 좀 확인해 드릴게요, 고객님.\n손님: 예, 예.\n상담사: 예, 고객님 오늘 보지 마시고요, 이제 확정된게 10월 15일부터 나오거든요? 10월 15일, 10월 대금 확정이 10월 15일에 되니까 10월 15일 이후에 이번 주 주말 이후에 그 애플리케이션에서 결제 당월 대금 명세서를 보시면 대금이 확인되실 거예요. \n손님: 알겠습니다. 10월 15일에 확정된다는 거죠?\n상담사: 네, 그래서 애플리케이션에서 10월 15일 이후에 보시면 됩니다.\n손님: 예, 이거는 이후에 보겠습니다. 예, 알겠습니다. 감사합니다. \n상담사: 네, 상담원 ▲▲▲이었습니다. \n손님: 예, 감사합니다.\n상담사: 네, 고맙습니다. \n손님: 예.\n\t                                        ",
		"consulting_time": "09:00"
	}
]