[
	{
		"source_id": "21107",
		"source": "하나카드",
		"consulting_date": "2025-08-09",
		"consulting_category": "한도상향 접수/처리 ",
		"client_gender": "남자",
		"client_age": "40대",
		"consulting_turns": "39",
		"consulting_length": 316,
		"consulting_content": "상담사: 상담원 ▲▲▲입니다. 한도 상향을 원하신다고 전달받았습니다.\n손님: 예, 맞습니다.\n상담사: 네, 한도는 심사를 통해서 한도 상향 가능 여부를 안내해 드릴 수 있습니다. 앞으로 꾸준히 사용할 수 있는 정기 한도로 원하십니까?\n손님: 예.\n상담사: 확인 감사합니다. 심사 접수를 위해서 신용 정보 조회 동의가 필요합니다. 동의해 주시겠습니까?\n손님: 예, 예.\n상담사: 상향 희망하시는 한도는 얼마이십니까?\n손님: 이런 것도 좀 말하기 그런데\n상담사: 희망 한도는 손님께서 말씀해 주셔야 돼서요. 뭐 ▲▲▲원, ▲▲원, 이런 식으로 말씀해주셔야 접수를 같이 해볼 수 있습니다.\n손님: 아 ▲▲원으로 해 보십시오.\n상담사: 그러니까 ▲▲▲원 추가해서 그럼 ▲▲원 말씀이세요? \n손님: 예.\n상담사: 현금 서비스 한도는 기존에 ▲▲원이었는데 그대로 유지를 원하십니까?\n손님: 뭐가 ▲▲▲이었다고요? \n상담사: 아 현금 서비스 한도요.\n손님: 아 현금 서비스는 안 해요. \n상담사: 예, 그럼 그 사용 신청하는 거를 그대로 ▲▲원으로 접수하겠습니다. 그리고 요청하신 ▲▲원 한도까지 심사해 보고 만약 전액이 어려우면 가능한 금액으로 사용해 드리는데 괜찮으십니까?\n손님: 예, 그 한 가지 여쭤볼 게 처음에 발급할 때는\n상담사: 네.\n손님: 가맹점 구글에 ▲▲인가 했던 걸로 아는데 왜 갑자기 다 풀어버리죠? \n상담사: 손님, ▲▲이라고 말씀하시는데 초기 한도는 예전에 ▲▲년도 ▲▲▲원이셨고요.\n손님: 아 ▲▲\n상담사: 그 다음에 ▲▲년도 한도가 하향되는데 그 오랜 기간 손님께서 카드 사용이 없으셔서 무실적으로 인해서 할인되셨던 걸로 확인되십니다.\n손님: 예, 아 그랬어요? 그래요, 볼게요.\n상담사: 예, 이거 접수를 도와드릴 텐데 몇 가지만 좀 여쭤보겠습니다. 한도 상향 심사 시 정확히 소득이 확인되면 유리합니다. 실례지만 직장인이세요, 개인사업자 대표자이세요? \n손님: 예.\n손님: 대표\n상담사: 작년도에 종합소득세를 납부하셨을까요?\n손님: 뭐를 다시 한 번 말씀\n상담사: 아 네, 작년도에 종합소득세 납부하셨습니까?\n손님: 예, 납부했어요. \n상담사: 그럼 소득 서류를 보내실 필요없이 공공 마이데이터 서비스로 실시간 스크래핑이 가능합니다. 서비스 이용에 동의하시겠습니까?\n손님: 예.\n상담사: 확인 감사합니다. ▲▲은행 예적금이 있으시면 심사에 도움이 됩니다. ▲▲은행 거래 중이실까요?\n손님: 예, 하고 있어요.\n상담사: 네, 확인 감사합니다. 요청하신 내용으로 접수하겠습니다.\n상담사: 손님, 확인해 보니 더 기다리실 필요 없이 바로 사용 가능하셔서 총 한도 ▲▲원으로 사용되었습니다.\n손님: 예, 알겠습니다.\n상담사: 감사합니다. 행복한 하루 되세요. 상담원 ▲▲▲였습니다.\n\t                                        ",
		"consulting_time": "16:30"
	}
]