[
	{
		"source_id": "27268",
		"source": "하나카드",
		"consulting_date": "2025-09-07",
		"consulting_category": "결제계좌 안내/변경",
		"client_gender": "남자",
		"client_age": "60대",
		"consulting_turns": "43",
		"consulting_length": 282,
		"consulting_content": "상담사: 상담원 ▲▲▲입니다.\n손님: 네, 수고 많습니다. 다름이 아니고요.\n상담사: 네.\n손님: 아 그거 저기 빠져 나가는 거 계좌 번호를 바꾸려고 그러는데 괜찮겠어요?\n상담사: 아 계좌 정보를 변경하신다는 걸까요?\n손님: 네, 네.\n상담사: 아 그러세요? 우선 본인 확인 위해서 ▲▲▲ 님 본인 맞으실까요?\n손님: 네, 네.\n상담사: 확인 감사합니다. 신용카드 납부하시는 계좌정보 변경해 드릴 거고요.\n상담사: 네, 그러면 변경하실 계좌번호와 은행명 말씀해 주시겠어요?\n손님: 은행은 상호은행이고요.\n상담사: 네, 상호은행이고요.\n손님: 네, 계좌 번호는.\n상담사: 네.\n손님: ▲▲▲▲▲▲▲▲▲▲\n상담사: 계좌 정보 먼저 확인해 볼 텐데요, 잠시만 기다려 주시겠습니까?\n손님: 네.\n상담사: 네, 기다려 주셔서 감사합니다. 신청하신 계좌로 바로 변경 진행해 드릴 거고요. 변경을 위한 녹취 절차 진행이 필요합니다. 에이알에스 연결해 드리면 신청하신 계좌정보 잘 들어보시고 동의하시면 1번을 동의하지 않으시면 2번 입력 부탁드립니다.\n손님: 알겠습니다.\n상담사: 확인 감사드립니다. 신청하신 계좌로 변경 완료되었고요. 다음 달 결제일은 8월 12일인데, 이 때부터 바로 지금 변경하신 계좌에서 출금 처리될 거고요.\n손님: 네.\n상담사: 그리고 이 카드로 이용하시는 현금 입출금 기능 있으시죠? 신용카드로.\n손님: 네, 네.\n상담사: 네, 그 기능은 변경 전 계좌에서만 이용할 수 있습니다.\n손님: 아 그 통장 그 거기로.\n상담사: 네, 그 계좌에서만 이용할 수 있어요. 다시 변경하신 계좌로 사용을 하고 싶다 하시면 은행을 방문하시거나 혹은 카드 재발급을 진행해 주셔야 합니다.\n손님: 아 그렇게 되는구나.\n손님: 그러면 거기에 카드 가지고 하는 재발급 받아도 되는 거예요?\n상담사: 그럼 카드 은행에 방문하셔가지고 기능 자체만 따로 부여하는 거는 재발급이 필요하지는 않아요.\n손님: 그냥 거기서 이제 그 바로 할 수 있게끔 된다는 얘기죠?\n상담사: 이 기능만 따로 부여해드리는 거예요.\n손님: 알겠습니다. 그럼 이 계좌로 이제 그냥 변경해가지고 이쪽으로 입출금 해도 되는 거죠? \n상담사: 네, 그렇죠. 손님 편하신 방법으로 진행하시는 거고요.\n손님: 예, 알겠습니다.\n상담사: 네, 감사합니다. 상담원 ▲▲▲이었습니다.\n손님: 네, 수고하세요. \n상담사: 네, 감사합니다.\n\t                                        ",
		"consulting_time": "16:00"
	}
]