[
	{
		"source_id": "22925",
		"source": "하나카드",
		"consulting_date": "2025-08-22",
		"consulting_category": "교육비",
		"client_gender": "남자",
		"client_age": "40대",
		"consulting_turns": "54",
		"consulting_length": 413,
		"consulting_content": "상담사: 상담원 ▲▲▲입니다.\n손님: 아 네. 자동납부하고 있는 것 중에\n손님: 그 아이들이 스쿨뱅킹 있거든요.\n상담사: 아 네.\n손님: 그걸 좀 변경해야 될 것 같아요, 카드에.\n손님: 없어진 카드로 돼 있어서.\n상담사: 아, 그러셨습니까? 알겠습니다. 같이 확인 후 업무 처리하겠습니다. 우리 ▲▲▲ 님 본인분 맞으십니까?\n손님: 네.\n상담사: 먼저 ▲▲카드 이용해주셔서 진심으로 감사드립니다. 말씀주신 내용 확인해볼게요. 잠시만 기다려주시겠습니까?\n손님: 다시 한번 얘기해주세요.\n상담사: 아, 제가 한번 확인해보도록 하겠습니다. 잠시만 기다려주시겠습니까?\n손님: 예.\n상담사: 기다려주셔서 감사합니다. 지금 현재 연결돼 있는 정보는 ▲▲초등학교 ▲▲▲ 학생이 자동 납부 연결 돼 있는 걸로 확인되고 있고요, 잠시만 더 기다려주시겠습니까?\n손님: 아 네.\n상담사: 기다려주셔서 감사합니다. 해당 학생은 지금 자동납부가 ▲▲카드로 이제 연결이 되어 있네요. 그러면은 이 연결돼 있는 카드가 일단은 현재 해지가 되어있기 때문에요. 일단 자동 납부 정보 먼저 해지할게요.\n손님: 아 네.\n상담사: 잠시만 더 기다려주시겠습니까?\n손님: 네.\n상담사: 기다려주셔서 감사합니다. 해지 처리 먼저 진행했고요. 그럼 다시 연결을 진행을 할 거예요. 학생 그 식별 번호는 저희 남아있는 정보로 활용을 할 거고요. 카드 같은 경우에는 지금 혹시 가지고 계신 카드 중에 어떤 카드로 하시겠어요?\n손님: ▲▲카드 그걸로 해 주세요.\n상담사: ▲▲카드로요. 잠시만 기다려주시겠습니까?\n손님: 네.\n상담사: 기다려주셔서 감사합니다. 학생정보만 한번 더 확인할게요. ▲▲초등학교 ▲▲▲ 학생이고, ▲▲년 ▲▲월 ▲▲일생 맞나요?\n손님: 네, 맞습니다.\n상담사: 잠시만 기다려주시겠습니까?\n손님: 네.\n상담사: 기다려주셔서 감사합니다. ▲▲카드로 다시 연결해드렸고요. 지금 이제 최종 승인은 행정실에서 이루어지는 점 참고 부탁드리겠습니다.\n손님: 네.\n손님: 아 네. 그러면 혹시 제가 카드 다른 카드 중에 자동 납부로 ▲▲카드 있는 것들 좀 확인할 수 있을까요?\n상담사: 아까 그 ▲▲카드로 했을 때요?\n손님: 예. 없어진 카드 중에 자동납부가 되어 있으면 또 바꿔야 돼 가지고요.\n상담사: 그러신가요? 알겠습니다. 잠시만 기다려주시겠습니까?\n손님: 네.\n손님: 살아 있는 카드면 그냥 냅둬도 되는데.\n상담사: 아무래도 네. 그럼 잠시만 기다려주시겠습니까? 최근 ▲▲개월 이용 내역으로 조회하는 거라서요, 잠시만요.\n손님: 네.\n상담사: 기다려주셔서 감사합니다. ▲▲카드 최근 내역 보니까 아무래도 그 대명스테이션 정기 결제 건 좀 확인이 되고 있고요. 이게 최근 ▲▲월 ▲▲일까지 승인 들어왔다가 지금 해지가 그 승인이 거절 됐거든요.\n손님: 네.\n손님: 아, ▲▲월 ▲▲일. 네, 금액이 얼마 나가는 거였나요, 그게?\n상담사: 그래서 이거 수요일까지\n상담사: 이거는 ▲▲▲▲원이 계속 승인 들어왔네요.\n손님: 아, 그랬는데 거절당한 거죠?\n상담사: 네, 맞아요.\n손님: 아 네. 그거하고 또 있나요?\n상담사: 이거랑 그 다음에 혹시 ▲▲월 달까지요. 엘지유플러스 통신 요금 자동이체 승인 됐었거든요. 그래서 이것도 한번 체크를 해 주시면 좋을 것 같고요. 쿠팡 와우 멤버십 또 ▲▲월 달까지는 승인 내역 있어요.\n손님: 아 네. 그런 거는\n손님: 제가 바꿀 수 있는 것들이니까 그 세 가지 들어가 있는 거죠?\n상담사: 지금 제가 다시 한번 검수를 했을 때 이렇게 보여지고 있고요. 혹시 저희 그 내역 중에요, 안 했을 것 같긴 한데 ▲▲월 ▲▲일 날에 교원프라퍼티 ▲▲▲▲▲원 이거는 자동결제 아니신 거죠?\n손님: 아 네. 그런 거 같습니다. 확인 감사합니다. 제가 다시 한번 확인해 볼게요.\n상담사: 네.\n상담사: 다른 문의하실 내용은 없으시고요?\n손님: 아 네.\n상담사: 다시 한번 ▲▲카드 이용해주셔서 진심으로 감사드리고요. 상담원 ▲▲▲이었습니다. 감사합니다.\n손님: 예, 감사합니다. 안녕히 계세요.",
		"consulting_time": "17:00"
	}
]