[
	{
		"source_id": "23929",
		"source": "하나카드",
		"consulting_date": "2025-08-27",
		"consulting_category": "결제일 안내/변경 ",
		"client_gender": "남자",
		"client_age": "50대",
		"consulting_turns": "16",
		"consulting_length": 138,
		"consulting_content": "상담사: ▲▲카드 ▲▲▲입니다. ▲▲▲ 님 본인 맞으신가요?\n손님: 예.\n상담사: 무엇을 도와드릴까요?\n손님: 그 인터넷 결제일이 ▲▲일 날로 돼 있는데 혹시라도 좀 바꿀 수 있나 해서요. \n상담사: 아 결제일 변경 말씀하십니까? 손님 ▲▲일로 ▲▲▲ 씨이면 그 결제 기간이요, 신용 기간이 ▲▲일부터 ▲▲까지신데요. ▲▲일로 변경하시면 ▲▲부터 ▲▲일까지 그러니까 어떤 게 더 편하신 것 같으세요., 손님? ▲▲일로 그냥 해 드릴까요?\n손님: 예, ▲▲일 날로 그 중간에 아니 뭐 이거 ▲▲일이 빠져서, ▲▲일에 빠져나가면 정신이 없어서.\n상담사: 네, 네.\n손님: 아니, 날짜를 하루로 다 맞춰 놓으려고 그러거든요? \n상담사: 아 그럼 ▲▲일부터 ▲▲까지 쓰신 금액이 ▲▲일에 청구되시고요. 어 지금 ▲▲월 ▲▲일에는 어 손님, 그 ▲▲월 ▲▲일부터 ▲▲월 ▲▲까지 쓴 금액이 나갑니다.\n손님: 예.\n상담사: 네, 잠시만 기다려 주세요.\n손님: 예.\n상담사: 변경 가능하시고요. 손님 지금 변경해드렸고 네, 그 기간에 대한 구조 변경에 따른 이용 기간도 손님 문자로 발송해 드렸습니다. 내용을 참고하시기 바랍니다.\n손님: 예.\n상담사: 네, 감사합니다. 저는 상담원 ▲▲▲이었습니다. \n손님: 예, 수고했어요. ",
		"consulting_time": "14:00"
	}
]