[
	{
		"source_id": "200281",
		"source": "하나카드",
		"consulting_date": "2025-08-03",
		"consulting_category": "결제계좌 안내/변경",
		"client_gender": "남자",
		"client_age": "40대",
		"consulting_turns": "35",
		"consulting_length": 226,
		"consulting_content": "상담사: 상담원 ▲▲▲입니다.\n손님: 예, 그 다름이 아니라 카드 그 대금이 두 번 빠져나간 거 같거든요.\n상담사: 아 그러셨어요? 확인해 보도록 하겠습니다. 우선 정보 확인을 위해서 이 ▲▲▲ 님 본인 맞으세요? \n손님: 네. \n상담사: 네, 확인을 위해 잠시만 기다려 주시겠습니까? \n손님: 네. \n상담사: 기다려주셔서 감사합니다. 저희 쪽에 추가 입금된 금액 총 ▲▲▲▲▲▲▲▲원이 확인되고 있고요. 이거는 지금 결제 계좌로 환급 처리 중에 있습니다.\n손님: 네. 그런가요.\n상담사: 오늘 오전 10시 반 이후부터 순차적으로 환급을 진행해드리고 있어요.\n손님: 아 네, 금일 중으로 입금되는 거죠? \n상담사: 네, 그렇습니다.\n손님: 그 그리고 그 뭐냐, 그 환급 처리하고 계좌번호로 그 입금 번호를 바꿔야 되나요, 아니면 그 지금 바꿔도 원래 그 환급하는 쪽으로 들어가나요? \n상담사: 지금 똑같이 ▲▲은행 쪽으로 환급 진행 중에 있기 때문에 지금 변경하셔도 상관없습니다.\n손님: 네. 아 그래요? 그러면 저기 이제 앞으로 나가는 계좌는 번호를 바꾸려고 하거든요. \n상담사: 네. \n상담사: 그러세요? 어느 은행으로 변경하시는 거예요? \n손님: ▲▲은행으로 바꿀 거고요.\n상담사: 예, 계좌 번호 말씀해 주세요.\n손님: ▲▲▲\n상담사: ▲▲▲\n손님: ▲▲▲▲▲▲▲\n상담사: 네. \n손님: 예. \n상담사: ▲▲▲\n손님: ▲▲\n상담사: ▲▲번이요. 확인해보도록 하겠습니다. 잠시만 기다려 주세요.\n손님: 네. \n상담사: 기다려주셔서 감사합니다. ▲▲카드 이용 대금 출금 이체 계좌 등록에 관한 접수 내용 확인하겠습니다. 생년월일 ▲▲년 ▲▲월 ▲▲일 ▲▲▲ 님의 명의로 된 ▲▲은행 계좌 번호 ▲▲▲▲로 신청하신 내용이 맞으세요? \n손님: 예. \n상담사: 신청한 계좌에서 출금되도록 계좌 등록을 처리해 드렸고요. 변경된 ▲▲은행 계좌에서는 ▲▲월 ▲▲일 청구분부터 출금될 거고요. 완료되었습니다.\n손님: 예, 알겠습니다. 일단 ▲▲은행으로 입금이 된다는 거죠? \n상담사: 네. \n손님: 네, 알겠습니다.\n상담사: 네, 상담원 ▲▲▲였습니다.\n손님: 네 네. ",
		"consulting_time": "14:30"
	}
]