[
	{
		"source_id": "22566",
		"source": "하나카드",
		"consulting_date": "2025-08-19",
		"consulting_category": "도난/분실 신청/해제",
		"client_gender": "남자",
		"client_age": "40대",
		"consulting_turns": "35",
		"consulting_length": 315,
		"consulting_content": "상담사: 상담원 ▲▲▲입니다.\n손님: 네, 그 카드가 분실돼서 지금 재발급을 신청을 했고요.\n상담사: 아 네, 손님.\n손님: 예, 분실 신청도 따로 해야 되나요?\n상담사: 아 네, 내역 한 번 조회해보겠습니다. ▲▲▲ 님 본인 맞으십니까?\n손님: 네.\n상담사: 아 예, 확인 감사합니다. 우선 재발급 이력 먼저 좀 봐 드릴게요, 손님.\n손님: 예.\n상담사: 지금 보니까 그 ▲▲ 카드 재발급이 진행이 됐거든요. 오늘 이 카드 어 분실 신고가 되어 있는지 좀 봐드릴게요.\n손님: 예.\n상담사: 어 분실 신고가 되어 있는지 여부도 같이 좀 확인해드릴게요. \n손님: 아 그거 쓰는 거는 안 했어요. 그래갖고 제가 지금 방금 제가 그런 걸 제가 수정을 하고 바로 연결한 거예요.\n상담사: 아 안 하셨어요?\n상담사: 그럼 이전 카드에 대해서는 분실 신고를 바로 좀 해 드릴까요?\n손님: 네, 네 그렇게 해도 돼요.\n상담사: 알겠습니다. 혹시 카드는 언제 어디서 분실하셨는지는 기억나실까요?\n손님: 모르겠어요, 한 ▲▲일이요.\n상담사: 아 아 ▲▲일정도요? 그러면은 10월 10일자로 해서 분실 신고 도와드리고요. 어 분실 장소 기억 안 나시니까 모름으로 일단 기재 도와드리겠습니다.\n손님: 네.\n상담사: 네, 연락 주신 손님 ▲▲▲ 손님 본인 이시고요. 연락 가능한 연락처 등록된 ▲▲▲▲▲▲에 ▲▲▲▲번 맞습니까?\n손님: 네, 맞아요.\n상담사: 네, 확인 감사합니다. 그리고 해당 카드로 마지막 거래 이력 있는지 좀 봐드릴게요. 손님 잠시만 기다려 주세요.\n손님: 예.\n상담사: 기다려주셔서 감사합니다. 지금 보니까 카드 실물로 거래하신 거는 아니고 다 간편결제 식으로 해서 거래를 해주셨던 거 같은데요.\n손님: 네, 결제해 드리면 될까요?\n상담사: 아 네, 그래서 오늘도 이제 그 ▲▲▲▲▲▲▲원 비바리 퍼블 리카라는 항목으로 거래된 내역이 있고요.\n손님: 예, 예.\n상담사: 네, 지금 분실 신고를 하게 되면은 이렇게 연결된 각종 간편 결제도 바로 이용은 안 되세요, 괜찮으신 걸까요?\n손님: 네, 알겠습니다.\n상담사: 네, 알겠습니다. 그럼 분실 등록돼서 지금부터 이용되지 않으니 안심하셔도 되구요. 새 카드 진행 발급하신 거 받으면 사용해 주시면 될 것 같애요.\n손님: 네, 알겠습니다.\n상담사: 네, 감사합니다. 아 손님 그리고 혹시 다른 카드나 핸드폰 분실하신 건 없으신 거죠?\n손님: 네, 여보세요?\n상담사: 알겠습니다. 즐거운 하루 되시고요. ▲▲▲이었습니다.\n손님: 네.\n\t                                        ",
		"consulting_time": "14:00"
	}
]